Workbook

Sheet Historiske finansielle tall
B2: TOMRA ASA
B4: Aksjekurs | C4: 104.8
B5: Antall aksjer | C5: 296040156
B6: Markedsverdi (NOK) | C6: =C4*C5 -> 3.1025008e+10
B9: EUR million | C9: 2018 | D9: 2019 | E9: 2020 | F9: 2021 | G9: 2022 | H9: 2023 | I9: 2024 | J9: 2025
B10: Operating revenues | C10: 895.4 | D10: 948.2 | E10: 927.1 | F10: 1074.3 | G10: 1204.8 | H10: 1288 | I10: 1348 | J10: 1318
B11: EBITA | C11: 130.5 | D11: 140 | E11: 141.9 | F11: 174.3 | G11: 160.4 | H11: 119 | I11: 176 | J11: 174
B12: Operating profit (EBIT) | C12: 112.3 | D12: 119.2 | E12: 121.2 | F12: 153 | G12: 143 | H12: 101 | I12: 156 | J12: 148
B13: Profit before taxes | C13: 107.6 | D13: 114.4 | E13: 99.1 | F13: 150.2 | G13: 138.2 | H13: 85 | I13: 131 | J13: 130
B14: Net cash flow from operating activities | C14: 106.8 | D14: 133.3 | E14: 159.5 | F14: 175 | G14: 114 | H14: 136.8 | I14: 235.5 | J14: 170.9
B15: Capital expenditure | C15: 76.9 | D15: 64.6 | E15: 56.9 | F15: 58.3 | G15: 82.3 | H15: 92.9 | I15: 118.3 | J15: 131.5
B16: Free cash flow | C16: =C14-C15 -> 29.9 | D16: =D14-D15 -> 68.7 | E16: =E14-E15 -> 102.6 | F16: =F14-F15 -> 116.7 | G16: =G14-G15 -> 31.7 | H16: =H14-H15 -> 43.9 | I16: =I14-I15 -> 117.2 | J16: =J14-J15 -> 39.4
B17: FCF conversion | C17: =C16/C11 -> 0.22911877 | D17: =D16/D11 -> 0.49071429 | E17: =E16/E11 -> 0.7230444 | F17: =F16/F11 -> 0.66953528 | G17: =G16/G11 -> 0.19763092 | H17: =H16/H11 -> 0.36890756 | I17: =I16/I11 -> 0.66590909 | J17: =J16/J11 -> 0.22643678
B19: ROCE | C19: n/a | D19: n/a | E19: 0.19 | F19: 0.229 | G19: 0.193 | H19: 0.173 | I19: 0.184 | J19: 0.152
B20: ROE | C20: 0.153 | D20: 0.162 | E20: 0.148 | F20: 0.193 | G20: 0.168 | H20: 0.099 | I20: 0.157 | J20: 0.157
B23: Revenue | C23: =C10 -> 895.4 | D23: =D10 -> 948.2 | E23: =E10 -> 927.1 | F23: =F10 -> 1074.3 | G23: =G10 -> 1204.8 | H23: =H10 -> 1288 | I23: =I10 -> 1348 | J23: =J10 -> 1318
B24: Cost of goods sold | C24: 511.8 | D24: 533.7 | E24: 519.9 | F24: 602.7 | G24: 705.5 | H24: 739.7 | I24: 764 | J24: 733
B25: Gross contribution | C25: =C23-C24 -> 383.6 | D25: =D23-D24 -> 414.5 | E25: =E23-E24 -> 407.2 | F25: =F23-F24 -> 471.6 | G25: =G23-G24 -> 499.3 | H25: =H23-H24 -> 548.3 | I25: =I23-I24 -> 584 | J25: =J23-J24 -> 585
B26: Gross margin | C26: =C25/C23 -> 0.42841188 | D26: =D25/D23 -> 0.43714406 | E26: =E25/E23 -> 0.43921907 | F26: =F25/F23 -> 0.43898352 | G26: =G25/G23 -> 0.41442563 | H26: =H25/H23 -> 0.42569876 | I26: =I25/I23 -> 0.43323442 | J26: =J25/J23 -> 0.44385432
B29: Inventory | C29: 145.5 | D29: 161.8 | E29: 142.5 | F29: 188.6 | G29: 225.4 | H29: 237.4 | I29: 225.5 | J29: 254.6
B30: Receivables | C30: 191.6 | D30: 203 | E30: 221.7 | F30: 267.4 | G30: 327.8 | H30: 361.1 | I30: 373.7 | J30: 400.6
B31: Contract assets | C31: 41 | D31: 29 | E31: 2.6 | F31: 3.8 | G31: 10.8 | H31: 9.7 | I31: 19.6 | J31: 16.5
B32: Contract liabilities | C32: 59.2 | D32: 49.9 | E32: 46.5 | F32: 57.8 | G32: 77.9 | H32: 64.8 | I32: 89.4 | J32: 83.2
B33: Trade payables | C33: 63.2 | D33: 50.9 | E33: 52.8 | F33: 64.5 | G33: 62.5 | H33: 73.5 | I33: 61.4 | J33: 75
B34: Other current liabilities | C34: 96.5 | D34: 92.8 | E34: 90.1 | F34: 121.2 | G34: 127.2 | H34: 202.3 | I34: 206 | J34: 184.8
B35: Working capital | C35: =C29+C30+C31-C32-C33-C34 -> 159.2 | D35: =D29+D30+D31-D32-D33-D34 -> 200.2 | E35: =E29+E30+E31-E32-E33-E34 -> 177.4 | F35: =F29+F30+F31-F32-F33-F34 -> 216.3 | G35: =G29+G30+G31-G32-G33-G34 -> 296.4 | H35: =H29+H30+H31-H32-H33-H34 -> 267.6 | I35: =I29+I30+I31-I32-I33-I34 -> 262 | J35: =J29+J30+J31-J32-J33-J34 -> 328.7
B36: Working capital relative to revenue | C36: =C35/C23 -> 0.17779763 | D36: =D35/D23 -> 0.21113689 | E36: =E35/E23 -> 0.19134937 | F36: =F35/F23 -> 0.20134041 | G36: =G35/G23 -> 0.24601594 | H36: =H35/H23 -> 0.20776398 | I36: =I35/I23 -> 0.19436202 | J36: =J35/J23 -> 0.24939302
C39: =D9 -> 2019 | D39: =E9 -> 2020 | E39: =F9 -> 2021 | F39: =G9 -> 2022 | G39: =H9 -> 2023 | H39: =I9 -> 2024 | I39: =J9 -> 2025
B40: Omsetning | C40: =D23 -> 948.2 | D40: =E23 -> 927.1 | E40: =F23 -> 1074.3 | F40: =G23 -> 1204.8 | G40: =H23 -> 1288 | H40: =I23 -> 1348 | I40: =J23 -> 1318
B41: Bruttomargin | C41: =D26 -> 0.43714406 | D41: =E26 -> 0.43921907 | E41: =F26 -> 0.43898352 | F41: =G26 -> 0.41442563 | G41: =H26 -> 0.42569876 | H41: =I26 -> 0.43323442 | I41: =J26 -> 0.44385432
C53: 2019 | D53: 2020 | E53: 2021 | F53: 2022 | G53: 2023 | H53: 2024 | I53: 2025
B54: Justert EBITA | C54: =D11 -> 140 | D54: =E11 -> 141.9 | E54: =F11 -> 174.3 | F54: =G11 -> 160.4 | G54: =H11 -> 119 | H54: =I11 -> 176 | I54: =J11 -> 174
B55: EBITA-margin | C55: =D11/D10 -> 0.14764818 | D55: =E11/E10 -> 0.15305792 | E55: =F11/F10 -> 0.16224518 | F55: =G11/G10 -> 0.13313413 | G55: =H11/H10 -> 0.092391304 | H55: =I11/I10 -> 0.1305638 | I55: =J11/J10 -> 0.13201821
B67: ´2018-2020 er rapportert i MNOK så har omgjort for å kunne sammenligne´
C68: 2019 | D68: 2020 | E68: 2021 | F68: 2022 | G68: 2023 | H68: 2024 | I68: 2025
B69: Arbeidskapital som andel av omsetning | C69: =D36 -> 0.21113689 | D69: =E36 -> 0.19134937 | E69: =F36 -> 0.20134041 | F69: =G36 -> 0.24601594 | G69: =H36 -> 0.20776398 | H69: =I36 -> 0.19436202 | I69: =J36 -> 0.24939302
B71: År | C71: 2020 | D71: 2021 | E71: 2022 | F71: 2023 | G71: 2024 | H71: 2025
B72: EBITA brukt i beregningen | C72: =E11 -> 141.9 | D72: =F11 -> 174.3 | E72: =G11 -> 160.4 | F72: 162 | G72: 181 | H72: 171
B73: ROCE brukt i beregningen | C73: =E19 -> 0.19 | D73: =F19 -> 0.229 | E73: =G19 -> 0.193 | F73: =H19 -> 0.173 | G73: =I19 -> 0.184 | H73: =J19 -> 0.152
B74: EBIT brukt i beregningen | C74: =E12 -> 121.2 | D74: =F12 -> 153 | E74: =G12 -> 143 | F74: 143 | G74: 162 | H74: 146
B75: Skattesats | C75: 0.245 | D75: 0.245 | E75: 0.245 | F75: 0.245 | G75: 0.245 | H75: 0.245
B76: NOPAT | C76: =C74*(1-C75) -> 91.506 | D76: =D74*(1-D75) -> 115.515 | E76: =E74*(1-E75) -> 107.965 | F76: =F74*(1-F75) -> 107.965 | G76: =G74*(1-G75) -> 122.31 | H76: =H74*(1-H75) -> 110.23
B77: Gjennomsnittlig sysselsatt kapital | C77: =C72/C73 -> 746.84211 | D77: =D72/D73 -> 761.13537 | E77: =E72/E73 -> 831.08808 | F77: =F72/F73 -> 936.41618 | G77: =G72/G73 -> 983.69565 | H77: =H72/H73 -> 1125
B78: ROIC- Proxy | C78: =C76/C77 -> 0.12252389 | D78: =D76/D77 -> 0.1517667 | E78: =E76/E77 -> 0.12990801 | F78: =F76/F77 -> 0.11529596 | G78: =G76/G77 -> 0.12433724 | H78: =H76/H77 -> 0.097982222
B79: Modell- WACC | C79: =WACC!C32 -> 0.08323486 | D79: 0.0832 | E79: 0.0832 | F79: 0.0832 | G79: 0.0832 | H79: 0.0832
B80: ROIC- Proxy - WACC | C80: =(C78-C79)*100000 -> 3928.903 | D80: =(D78-D79)*100000 -> 6856.6695 | E80: =(E78-E79)*100000 -> 4670.8011 | F80: =(F78-F79)*100000 -> 3209.5957 | G80: =(G78-G79)*100000 -> 4113.7238 | H80: =(H78-H79)*100000 -> 1478.2222
C82: =C71 -> 2020 | D82: =D71 -> 2021 | E82: =E71 -> 2022 | F82: =F71 -> 2023 | G82: =G71 -> 2024 | H82: =H71 -> 2025
B83: =B78 -> ROIC- Proxy | C83: =C78 -> 0.12252389 | D83: =D78 -> 0.1517667 | E83: =E78 -> 0.12990801 | F83: =F78 -> 0.11529596 | G83: =G78 -> 0.12433724 | H83: =H78 -> 0.097982222
B84: =B79 -> Modell- WACC | C84: =C79 -> 0.08323486 | D84: =D79 -> 0.0832 | E84: =E79 -> 0.0832 | F84: =F79 -> 0.0832 | G84: =G79 -> 0.0832 | H84: =H79 -> 0.0832
B101: Bidrag til netto arbeidskapital | C101: 2024 | D101: 2025 | E101: Bidrag til endringen
B102: Varelager | C102: =I29 -> 225.5 | D102: =J29 -> 254.6 | E102: =D102-C102 -> 29.1
B103: Kundefordringer | C103: =I30 -> 373.7 | D103: =J30 -> 400.6 | E103: =D103-C103 -> 26.9
B104: Kontraktseiendeler | C104: =I31 -> 19.6 | D104: =J31 -> 16.5 | E104: =D104-C104 -> -3.1
B105: Kontraktsforpliktelser | C105: =I32 -> 89.4 | D105: =J32 -> 83.2 | E105: =C105-D105 -> 6.2
B106: Leverandørgjeld | C106: =I33 -> 61.4 | D106: =J33 -> 75 | E106: =C106-D106 -> -13.6
B107: Andre kortsiktige forpliktelser | C107: =I34 -> 206 | D107: =J34 -> 184.8 | E107: =C107-D107 -> 21.2
B108: Netto arbeidskapital | C108: =I35 -> 262 | D108: =J35 -> 328.7 | E108: =D108-C108 -> 66.7

Sheet WACC
B2: WACC-Beregning
B4: Risikofri rente | C4: 0.0446 | E4: Kilde: https://tradingeconomics.com/norway/government-bond-yield
B5: Markedets risikopremie | C5: 0.0525
B6: Beta | C6: =(SLOPE(D40:D1295,F40:F1295))*2/3+1/3 -> 0.91486792
B7: Landrisikopremie | C7: 0
B8: Kostnad på egenkapital | C8: =C4+C6*C5+C7 -> 0.092630566
B11: Kostnad på gjeld f/skatt | C11: 0.055
B12: Skattesats | C12: ='Forecast Base'!C57 -> 0.245
B13: Kostnad på gjeld etter skatt | C13: =C11*(1-C12) -> 0.041525
B16: Aksjekurs i NOK | C16: ='Historiske finansielle tall'!C4 -> 104.8
B17: Antall aksjer | C17: ='Historiske finansielle tall'!C5 -> 296040156
B18: Markedsverdi egenkapital, NOK mill | C18: =(C16*C17)/1000000 -> 31025.008
B19: Netto rentebærende gjeld, NOK mill | C19: =DCF!C21*DCF!C6 -> 5361.72
B20: Leasinggjeld, NOK mill | C20: =DCF!C22*DCF!C6 -> 1627.08
B21: Gjeld brukt i WACC | C21: =C19+C20 -> 6988.8
B22: Totalkapital | C22: =C18+C21 -> 38013.808
B23: Egenkapitalvekt | C23: =C18/C22 -> 0.81615102
B24: Gjeldsvekt | C24: =C21/C22 -> 0.18384898
B26: Kontroll | C26: =C23+C24 -> 1
B28: Egenkapitalvekt | C28: =C23 -> 0.81615102
B29: Kostnad på egenkapital | C29: =C8 -> 0.092630566
B30: Gjeldsvekt | C30: =C24 -> 0.18384898
B31: Gjeldskostnad etter skatt | C31: =C13 -> 0.041525
B32: WACC | C32: =C28*C29+C30*C31 -> 0.08323486
B34: *Alle data hentet 31.juli 2026*
B37: UTREGNING BETA
B38: Dato ukeslutt | C38: TOMRA Kurs | D38: Endring | E38: OSEBX kurs | F38: Endring
B39: 44414 | C39: 255.8 | E39: 1145.55
B40: 44421 | C40: 258.4 | D40: =(C40-C39)/C39 -> 0.010164191 | E40: 1159 | F40: =(E40-E39)/E39 -> 0.011741085
B41: 44428 | C41: 260.7 | D41: =(C41-C40)/C40 -> 0.0089009288 | E41: 1133.18 | F41: =(E41-E40)/E40 -> -0.022277826
B42: 44435 | C42: 262.8 | D42: =(C42-C41)/C41 -> 0.0080552359 | E42: 1164.58 | F42: =(E42-E41)/E41 -> 0.027709631
B43: 44442 | C43: 262.2 | D43: =(C43-C42)/C42 -> -0.002283105 | E43: 1161.86 | F43: =(E43-E42)/E42 -> -0.002335606
B44: 44449 | C44: 256.6 | D44: =(C44-C43)/C43 -> -0.021357742 | E44: 1152.02 | F44: =(E44-E43)/E43 -> -0.0084691787
B45: 44456 | C45: 240.65 | D45: =(C45-C44)/C44 -> -0.062159002 | E45: 1141.17 | F45: =(E45-E44)/E44 -> -0.0094182393
B46: 44463 | C46: 244.45 | D46: =(C46-C45)/C45 -> 0.015790567 | E46: 1155 | F46: =(E46-E45)/E45 -> 0.012119141
B47: 44470 | C47: 226.5 | D47: =(C47-C46)/C46 -> -0.073430149 | E47: 1164.43 | F47: =(E47-E46)/E46 -> 0.0081645022
B48: 44477 | C48: 232 | D48: =(C48-C47)/C47 -> 0.024282561 | E48: 1167.35 | F48: =(E48-E47)/E47 -> 0.0025076647
B49: 44484 | C49: 241.15 | D49: =(C49-C48)/C48 -> 0.039439655 | E49: 1197.57 | F49: =(E49-E48)/E48 -> 0.025887694
B50: 44491 | C50: 258.3 | D50: =(C50-C49)/C49 -> 0.071117562 | E50: 1217.71 | F50: =(E50-E49)/E49 -> 0.016817389
B51: 44498 | C51: 272.6 | D51: =(C51-C50)/C50 -> 0.055361982 | E51: 1192.78 | F51: =(E51-E50)/E50 -> -0.020472855
... B299: 46234 | C299: 104.8 | D299: =(C299-C298)/C298 -> 0.043824701 | E299: 2018.08 | F299: =(E299-E298)/E298 -> 0.0052552141

Sheet Antagelser
A1: Base forutsetninger
C2: 2026E | D2: 2027E | E2: 2028E | F2: 2029E | G2: 2030E | H2: 2031E | I2: 2032E | J2: 2033E | K2: 2034E | L2: 2035E
B3: Collection
B4: Omsetningsvekst | C4: 0.18 | D4: 0.08 | E4: 0.07 | F4: 0.06 | G4: 0.06 | H4: 0.055 | I4: 0.05 | J4: 0.045 | K4: 0.04 | L4: 0.035
B5: Bruttomargin | C5: 0.4 | D5: 0.405 | E5: 0.405 | F5: 0.405 | G5: 0.405 | H5: 0.405 | I5: 0.405 | J5: 0.405 | K5: 0.405 | L5: 0.405
B6: Vekst i driftskostnader | C6: 0.09 | D6: 0.04 | E6: 0.05 | F6: 0.05 | G6: 0.05 | H6: 0.05 | I6: 0.05 | J6: 0.045 | K6: 0.045 | L6: 0.04
B8: Recycling
B9: Omsetningsvekst | C9: -0.05 | D9: 0.08 | E9: 0.1 | F9: 0.08 | G9: 0.07 | H9: 0.055 | I9: 0.05 | J9: 0.045 | K9: 0.035 | L9: 0.03
B10: Bruttomargin | C10: 0.47 | D10: 0.49 | E10: 0.505 | F10: 0.515 | G10: 0.52 | H10: 0.52 | I10: 0.52 | J10: 0.52 | K10: 0.52 | L10: 0.52
B11: Vekst i driftskostnader | C11: -0.06 | D11: 0.02 | E11: 0.04 | F11: 0.04 | G11: 0.04 | H11: 0.04 | I11: 0.04 | J11: 0.04 | K11: 0.035 | L11: 0.03
B13: Food
B14: Omsetningsvekst | C14: 0.07 | D14: 0.07 | E14: 0.07 | F14: 0.065 | G14: 0.06 | H14: 0.0525 | I14: 0.05 | J14: 0.045 | K14: 0.04 | L14: 0.03
B15: Bruttomargin | C15: 0.44 | D15: 0.45 | E15: 0.455 | F15: 0.455 | G15: 0.455 | H15: 0.455 | I15: 0.455 | J15: 0.455 | K15: 0.455 | L15: 0.455
B16: Vekst i driftskostnader | C16: 0.05 | D16: 0.04 | E16: 0.04 | F16: 0.04 | G16: 0.04 | H16: 0.04 | I16: 0.04 | J16: 0.04 | K16: 0.04 | L16: 0.04
B19: Amortisering/omsetning | C19: 0.02 | D19: 0.019 | E19: 0.018 | F19: 0.017 | G19: 0.017 | H19: 0.016 | I19: 0.015 | J19: 0.014 | K19: 0.013 | L19: 0.012
B20: Skattesats | C20: 0.245 | D20: 0.245 | E20: 0.245 | F20: 0.245 | G20: 0.245 | H20: 0.245 | I20: 0.245 | J20: 0.245 | K20: 0.245 | L20: 0.245
B21: D&A/omsetning | C21: 0.085 | D21: 0.083 | E21: 0.08 | F21: 0.078 | G21: 0.075 | H21: 0.073 | I21: 0.071 | J21: 0.069 | K21: 0.067 | L21: 0.065
B22: Capex/Omsetning | C22: 0.1 | D22: 0.095 | E22: 0.09 | F22: 0.085 | G22: 0.08 | H22: 0.078 | I22: 0.078 | J22: 0.078 | K22: 0.078 | L22: 0.078
B23: Arbeidskapital/Omsetning | C23: 0.25 | D23: 0.245 | E23: 0.24 | F23: 0.235 | G23: 0.23 | H23: 0.23 | I23: 0.228 | J23: 0.226 | K23: 0.225 | L23: 0.225
A27: Bear forutsetninger
C28: 2026E | D28: 2027E | E28: 2028E | F28: 2029E | G28: 2030E | H28: =H2 -> 2031E | I28: =I2 -> 2032E | J28: =J2 -> 2033E | K28: =K2 -> 2034E | L28: =L2 -> 2035E
B29: Collection
B30: Omsetningsvekst | C30: 0.16 | D30: 0.07 | E30: 0.06 | F30: 0.05 | G30: 0.05 | H30: 0.045 | I30: 0.04 | J30: 0.035 | K30: 0.03 | L30: 0.025
B31: Bruttomargin | C31: 0.395 | D31: 0.4 | E31: 0.4 | F31: 0.402 | G31: 0.402 | H31: 0.402 | I31: 0.404 | J31: 0.405 | K31: 0.405 | L31: 0.405
B32: Vekst i driftskostnader | C32: 0.095 | D32: 0.05 | E32: 0.05 | F32: 0.055 | G32: 0.055 | H32: 0.045 | I32: 0.042 | J32: 0.04 | K32: 0.038 | L32: 0.035
B34: Recycling
B35: Omsetningsvekst | C35: -0.08 | D35: 0.05 | E35: 0.08 | F35: 0.07 | G35: 0.07 | H35: 0.045 | I35: 0.045 | J35: 0.04 | K35: 0.035 | L35: 0.03
B36: Bruttomargin | C36: 0.45 | D36: 0.47 | E36: 0.485 | F36: 0.495 | G36: 0.5 | H36: 0.505 | I36: 0.51 | J36: 0.513 | K36: 0.515 | L36: 0.515
B37: Vekst i driftskostnader | C37: -0.05 | D37: 0.03 | E37: 0.05 | F37: 0.05 | G37: 0.05 | H37: 0.03 | I37: 0.032 | J37: 0.032 | K37: 0.03 | L37: 0.028
B39: Food
B40: Omsetningsvekst | C40: 0.05 | D40: 0.05 | E40: 0.05 | F40: 0.045 | G40: 0.04 | H40: 0.04 | I40: 0.04 | J40: 0.035 | K40: 0.03 | L40: 0.025
B41: Bruttomargin | C41: 0.425 | D41: 0.435 | E41: 0.435 | F41: 0.44 | G41: 0.445 | H41: 0.448 | I41: 0.45 | J41: 0.452 | K41: 0.453 | L41: 0.455
B42: Vekst i driftskostnader | C42: 0.06 | D42: 0.05 | E42: 0.05 | F42: 0.05 | G42: 0.05 | H42: 0.035 | I42: 0.035 | J42: 0.033 | K42: 0.03 | L42: 0.028
B45: Amortisering/omsetning | C45: 0.02 | D45: 0.019 | E45: 0.018 | F45: 0.017 | G45: 0.017 | H45: 0.016 | I45: 0.015 | J45: 0.014 | K45: 0.013 | L45: 0.012
B46: Skattesats | C46: 0.25 | D46: 0.25 | E46: 0.25 | F46: 0.25 | G46: 0.25 | H46: 0.25 | I46: 0.25 | J46: 0.25 | K46: 0.25 | L46: 0.25
B47: D&A/omsetning | C47: 0.085 | D47: 0.083 | E47: 0.08 | F47: 0.078 | G47: 0.075 | H47: 0.073 | I47: 0.071 | J47: 0.069 | K47: 0.067 | L47: 0.065
B48: Capex/Omsetning | C48: 0.105 | D48: 0.1 | E48: 0.095 | F48: 0.09 | G48: 0.085 | H48: 0.088 | I48: 0.086 | J48: 0.084 | K48: 0.082 | L48: 0.08
B49: Arbeidskapital/Omsetning | C49: 0.255 | D49: 0.25 | E49: 0.245 | F49: 0.24 | G49: 0.235 | H49: 0.235 | I49: 0.233 | J49: 0.23 | K49: 0.228 | L49: 0.225
A53: Bull forutsetinger
C54: 2026E | D54: 2027E | E54: 2028E | F54: 2029E | G54: 2030E | H54: 2031E | I54: 2032E | J54: 2033E | K54: 2034E | L54: 2035E
B55: Collection
B56: Omsetningsvekst | C56: 0.19 | D56: 0.09 | E56: 0.09 | F56: 0.085 | G56: 0.08 | H56: 0.065 | I56: 0.06 | J56: 0.055 | K56: 0.05 | L56: 0.045
B57: Bruttomargin | C57: 0.41 | D57: 0.415 | E57: 0.415 | F57: 0.418 | G57: 0.418 | H57: 0.418 | I57: 0.418 | J57: 0.418 | K57: 0.418 | L57: 0.418
B58: Vekst i driftskostnader | C58: 0.08 | D58: 0.03 | E58: 0.04 | F58: 0.04 | G58: 0.04 | H58: 0.065 | I58: 0.06 | J58: 0.055 | K58: 0.05 | L58: 0.045
B60: Recycling
B61: Omsetningsvekst | C61: -0.03 | D61: 0.1 | E61: 0.12 | F61: 0.1 | G61: 0.085 | H61: 0.065 | I61: 0.06 | J61: 0.055 | K61: 0.05 | L61: 0.04
B62: Bruttomargin | C62: 0.48 | D62: 0.5 | E62: 0.515 | F62: 0.525 | G62: 0.53 | H62: 0.53 | I62: 0.53 | J62: 0.53 | K62: 0.53 | L62: 0.53
B63: Vekst i driftskostnader | C63: -0.07 | D63: 0.01 | E63: 0.03 | F63: 0.04 | G63: 0.04 | H63: 0.065 | I63: 0.06 | J63: 0.055 | K63: 0.05 | L63: 0.04
B65: Food
B66: Omsetningsvekst | C66: 0.075 | D66: 0.08 | E66: 0.08 | F66: 0.08 | G66: 0.08 | H66: 0.06 | I66: 0.055 | J66: 0.05 | K66: 0.045 | L66: 0.04
B67: Bruttomargin | C67: 0.44 | D67: 0.46 | E67: 0.46 | F67: 0.465 | G67: 0.465 | H67: 0.465 | I67: 0.465 | J67: 0.465 | K67: 0.465 | L67: 0.465
B68: Vekst i driftskostnader | C68: 0.04 | D68: 0.03 | E68: 0.03 | F68: 0.03 | G68: 0.03 | H68: 0.06 | I68: 0.055 | J68: 0.05 | K68: 0.045 | L68: 0.04
B71: Amortisering/omsetning | C71: 0.02 | D71: 0.019 | E71: 0.018 | F71: 0.017 | G71: 0.017 | H71: 0.016 | I71: 0.015 | J71: 0.014 | K71: 0.013 | L71: 0.012
B72: Skattesats | C72: 0.24 | D72: 0.24 | E72: 0.24 | F72: 0.24 | G72: 0.24 | H72: 0.24 | I72: 0.24 | J72: 0.24 | K72: 0.24 | L72: 0.24
B73: D&A/omsetning | C73: 0.085 | D73: 0.083 | E73: 0.08 | F73: 0.078 | G73: 0.075 | H73: 0.073 | I73: 0.071 | J73: 0.069 | K73: 0.067 | L73: 0.065
B74: Capex/Omsetning | C74: 0.095 | D74: 0.085 | E74: 0.08 | F74: 0.075 | G74: 0.07 | H74: 0.07 | I74: 0.07 | J74: 0.069 | K74: 0.068 | L74: 0.068
B75: Arbeidskapital/Omsetning | C75: 0.24 | D75: 0.225 | E75: 0.21 | F75: 0.205 | G75: 0.2 | H75: 0.2 | I75: 0.198 | J75: 0.197 | K75: 0.196 | L75: 0.195

Sheet Forecast Base
B2: Forecast Base
B4: COLLECTION | C4: 2023 | D4: 2024 | E4: 2025 | F4: 2026E | G4: 2027E | H4: 2028E | I4: 2029E | J4: 2030E | K4: 2031E | L4: 2032E | M4: 2033E | N4: 2034E | O4: 2035E
B5: Omsetning | C5: 697.4 | D5: 773.1 | E5: 740.5 | F5: =E5*(1+Antagelser!C4) -> 873.79 | G5: =F5*(1+Antagelser!D4) -> 943.6932 | H5: =G5*(1+Antagelser!E4) -> 1009.7517 | I5: =H5*(1+Antagelser!F4) -> 1070.3368 | J5: =I5*(1+Antagelser!G4) -> 1134.557 | K5: =J5*(1+Antagelser!H4) -> 1196.9577 | L5: =K5*(1+Antagelser!I4) -> 1256.8056 | M5: =L5*(1+Antagelser!J4) -> 1313.3618 | ... O5: =N5*(1+Antagelser!L4) -> 1413.7027
B6: Vekst | D6: =(D5-C5)/C5 -> 0.10854603 | E6: =(E5-D5)/D5 -> -0.042167895 | F6: =(F5-E5)/E5 -> 0.18 | G6: =(G5-F5)/F5 -> 0.08 | H6: =(H5-G5)/G5 -> 0.07 | I6: =(I5-H5)/H5 -> 0.06 | J6: =(J5-I5)/I5 -> 0.06 | K6: =(K5-J5)/J5 -> 0.055 | ... O6: =(O5-N5)/N5 -> 0.035
B7: Bruttomargin | C7: 0.399 | D7: 0.406 | E7: 0.417 | F7: =Antagelser!C5 -> 0.4 | G7: =Antagelser!D5 -> 0.405 | H7: =Antagelser!E5 -> 0.405 | I7: =Antagelser!F5 -> 0.405 | J7: =Antagelser!G5 -> 0.405 | K7: =Antagelser!H5 -> 0.405 | L7: =Antagelser!I5 -> 0.405 | M7: =Antagelser!J5 -> 0.405 | ... O7: =Antagelser!L5 -> 0.405
B8: Bruttobidrag | C8: =C5*C7 -> 278.2626 | D8: =D5*D7 -> 313.8786 | E8: =E5*E7 -> 308.7885 | F8: =F5*F7 -> 349.516 | G8: =G5*G7 -> 382.19575 | H8: =H5*H7 -> 408.94945 | I8: =I5*I7 -> 433.48642 | J8: =J5*J7 -> 459.4956 | ... O8: =O5*O7 -> 572.54957
B9: Driftskostnader | C9: 162.9 | D9: 183.2 | E9: 182.4 | F9: =E9*(1+Antagelser!C6) -> 198.816 | G9: =F9*(1+Antagelser!D6) -> 206.76864 | H9: =G9*(1+Antagelser!E6) -> 217.10707 | I9: =H9*(1+Antagelser!F6) -> 227.96243 | J9: =I9*(1+Antagelser!G6) -> 239.36055 | K9: =J9*(1+Antagelser!H6) -> 251.32857 | L9: =K9*(1+Antagelser!I6) -> 263.895 | M9: =L9*(1+Antagelser!J6) -> 275.77028 | ... O9: =N9*(1+Antagelser!L6) -> 299.70714
B10: Justert EBITA | C10: =C8-C9 -> 115.3626 | D10: =D8-D9 -> 130.6786 | E10: =E8-E9 -> 126.3885 | F10: =F8-F9 -> 150.7 | G10: =G8-G9 -> 175.42711 | H10: =H8-H9 -> 191.84238 | I10: =I8-I9 -> 205.52399 | J10: =J8-J9 -> 220.13505 | ... O10: =O8-O9 -> 272.84244
B11: Justert EBITA-margin | C11: =C10/C5 -> 0.16541812 | D11: =D10/D5 -> 0.16903195 | E11: =E10/E5 -> 0.17067995 | F11: =F10/F5 -> 0.17246707 | G11: =G10/G5 -> 0.18589421 | H11: =H10/H5 -> 0.18998965 | I11: =I10/I5 -> 0.19201805 | J11: =J10/J5 -> 0.19402731 | ... O11: =O10/O5 -> 0.19299846
B13: RECYCLING
B14: Omsetning | C14: 270.1 | D14: 265.8 | E14: 218.2 | F14: =E14*(1+Antagelser!C9) -> 207.29 | G14: =F14*(1+Antagelser!D9) -> 223.8732 | H14: =G14*(1+Antagelser!E9) -> 246.26052 | I14: =H14*(1+Antagelser!F9) -> 265.96136 | J14: =I14*(1+Antagelser!G9) -> 284.57866 | K14: =J14*(1+Antagelser!H9) -> 300.23048 | L14: =K14*(1+Antagelser!I9) -> 315.24201 | M14: =L14*(1+Antagelser!J9) -> 329.4279 | ... O14: =N14*(1+Antagelser!L9) -> 351.18661
B15: Vekst | D15: =(D14-C14)/C14 -> -0.01592003 | E15: =(E14-D14)/D14 -> -0.17908202 | F15: =(F14-E14)/E14 -> -0.05 | G15: =(G14-F14)/F14 -> 0.08 | H15: =(H14-G14)/G14 -> 0.1 | I15: =(I14-H14)/H14 -> 0.08 | J15: =(J14-I14)/I14 -> 0.07 | K15: =(K14-J14)/J14 -> 0.055 | ... O15: =(O14-N14)/N14 -> 0.03
B16: Bruttomargin | C16: 0.522 | D16: 0.525 | E16: 0.477 | F16: =Antagelser!C10 -> 0.47 | G16: =Antagelser!D10 -> 0.49 | H16: =Antagelser!E10 -> 0.505 | I16: =Antagelser!F10 -> 0.515 | J16: =Antagelser!G10 -> 0.52 | K16: =Antagelser!H10 -> 0.52 | L16: =Antagelser!I10 -> 0.52 | M16: =Antagelser!J10 -> 0.52 | ... O16: =Antagelser!L10 -> 0.52
B17: Bruttobidrag | C17: =C16*C14 -> 140.9922 | D17: =D16*D14 -> 139.545 | E17: =E16*E14 -> 104.0814 | F17: =F16*F14 -> 97.4263 | G17: =G16*G14 -> 109.69787 | H17: =H16*H14 -> 124.36156 | I17: =I16*I14 -> 136.9701 | J17: =J16*J14 -> 147.9809 | ... O17: =O16*O14 -> 182.61704
B18: Driftskostnader | C18: 79.5 | D18: 79.4 | E18: 80.6 | F18: =E18*(1+Antagelser!C11) -> 75.764 | G18: =F18*(1+Antagelser!D11) -> 77.27928 | H18: =G18*(1+Antagelser!E11) -> 80.370451 | I18: =H18*(1+Antagelser!F11) -> 83.585269 | J18: =I18*(1+Antagelser!G11) -> 86.92868 | K18: =J18*(1+Antagelser!H11) -> 90.405827 | L18: =K18*(1+Antagelser!I11) -> 94.02206 | M18: =L18*(1+Antagelser!J11) -> 97.782943 | ... O18: =N18*(1+Antagelser!L11) -> 104.24151
B19: Justert EBITA | C19: =C17-C18 -> 61.4922 | D19: =D17-D18 -> 60.145 | E19: =E17-E18 -> 23.4814 | F19: =F17-F18 -> 21.6623 | G19: =G17-G18 -> 32.418588 | H19: =H17-H18 -> 43.991111 | I19: =I17-I18 -> 53.384832 | J19: =J17-J18 -> 61.052222 | ... O19: =O17-O18 -> 78.375531
B20: Justert EBITA-margin | C20: =C19/C14 -> 0.22766457 | D20: =D19/D14 -> 0.22627916 | E20: =E19/E14 -> 0.10761412 | F20: =F19/F14 -> 0.10450239 | G20: =G19/G14 -> 0.14480781 | H20: =H19/H14 -> 0.17863648 | I20: =I19/I14 -> 0.20072401 | J20: =J19/J14 -> 0.21453549 | ... O20: =O19/O14 -> 0.22317346
B22: FOOD
B23: Omsetning | C23: 319.6 | D23: 310.9 | E23: 328 | F23: =E23*(1+Antagelser!C14) -> 350.96 | G23: =F23*(1+Antagelser!D14) -> 375.5272 | H23: =G23*(1+Antagelser!E14) -> 401.8141 | I23: =H23*(1+Antagelser!F14) -> 427.93202 | J23: =I23*(1+Antagelser!G14) -> 453.60794 | K23: =J23*(1+Antagelser!H14) -> 477.42236 | L23: =K23*(1+Antagelser!I14) -> 501.29348 | M23: =L23*(1+Antagelser!J14) -> 523.85168 | ... O23: =N23*(1+Antagelser!L14) -> 561.14992
B24: Vekst | D24: =(D23-C23)/C23 -> -0.027221527 | E24: =(E23-D23)/D23 -> 0.055001608 | F24: =(F23-E23)/E23 -> 0.07 | G24: =(G23-F23)/F23 -> 0.07 | H24: =(H23-G23)/G23 -> 0.07 | I24: =(I23-H23)/H23 -> 0.065 | J24: =(J23-I23)/I23 -> 0.06 | K24: =(K23-J23)/J23 -> 0.0525 | ... O24: =(O23-N23)/N23 -> 0.03
B25: Bruttomargin | C25: 0.407 | D25: 0.429 | E25: 0.469 | F25: =Antagelser!C15 -> 0.44 | G25: =Antagelser!D15 -> 0.45 | H25: =Antagelser!E15 -> 0.455 | I25: =Antagelser!F15 -> 0.455 | J25: =Antagelser!G15 -> 0.455 | K25: =Antagelser!H15 -> 0.455 | L25: =Antagelser!I15 -> 0.455 | M25: =Antagelser!J15 -> 0.455 | ... O25: =Antagelser!L15 -> 0.455
B26: Bruttobidrag | C26: =C23*C25 -> 130.0772 | D26: =D23*D25 -> 133.3761 | E26: =E23*E25 -> 153.832 | F26: =F23*F25 -> 154.4224 | G26: =G23*G25 -> 168.98724 | H26: =H23*H25 -> 182.82542 | I26: =I23*I25 -> 194.70907 | J26: =J23*J25 -> 206.39161 | ... O26: =O23*O25 -> 255.32322
B27: Driftskostnader | C27: 122.4 | D27: 112.6 | E27: 110.3 | F27: =E27*(1+Antagelser!C16) -> 115.815 | G27: =F27*(1+Antagelser!D16) -> 120.4476 | H27: =G27*(1+Antagelser!E16) -> 125.2655 | I27: =H27*(1+Antagelser!F16) -> 130.27612 | J27: =I27*(1+Antagelser!G16) -> 135.48717 | K27: =J27*(1+Antagelser!H16) -> 140.90666 | L27: =K27*(1+Antagelser!I16) -> 146.54292 | M27: =L27*(1+Antagelser!J16) -> 152.40464 | ... O27: =N27*(1+Antagelser!L16) -> 164.84086
B28: Justert EBITA | C28: =C26-C27 -> 7.6772 | D28: =D26-D27 -> 20.7761 | E28: =E26-E27 -> 43.532 | F28: =F26-F27 -> 38.6074 | G28: =G26-G27 -> 48.53964 | H28: =H26-H27 -> 57.559913 | I28: =I26-I27 -> 64.432945 | J28: =J26-J27 -> 70.904444 | ... O28: =O26-O27 -> 90.482358
B29: Justert EBITA-margin | C29: =C28/C23 -> 0.024021277 | D29: =D28/D23 -> 0.066825667 | E29: =E28/E23 -> 0.13271951 | F29: =F28/F23 -> 0.11000513 | G29: =G28/G23 -> 0.12925732 | H29: =H28/H23 -> 0.14325011 | I29: =I28/I23 -> 0.15056818 | J29: =J28/J23 -> 0.15631218 | ... O29: =O28/O23 -> 0.16124453
B31: HORIZON
B32: Omsetning | C32: 0.8 | D32: 7.4 | E32: 32.3 | F32: 48 | G32: 60 | H32: 75 | I32: 90 | J32: 105 | K32: 118 | L32: 130 | M32: 141 | N32: 151 | O32: 160
B33: Vekst | D33: =(D32-C32)/C32 -> 8.25 | E33: =(E32-D32)/D32 -> 3.3648649 | F33: =(F32-E32)/E32 -> 0.48606811 | G33: =(G32-F32)/F32 -> 0.25 | H33: =(H32-G32)/G32 -> 0.25 | I33: =(I32-H32)/H32 -> 0.2 | J33: =(J32-I32)/I32 -> 0.16666667 | K33: =(K32-J32)/J32 -> 0.12380952 | ... O33: =(O32-N32)/N32 -> 0.059602649
B34: Bruttomargin | C34: -1.194 | D34: 0.501 | E34: 0.594 | F34: 0.6 | G34: 0.62 | H34: 0.63 | I34: 0.64 | J34: 0.65 | K34: 0.655 | L34: 0.66 | M34: 0.66 | N34: 0.66 | O34: 0.66
B35: Bruttobidrag | C35: =C34*C32 -> -0.9552 | D35: =D34*D32 -> 3.7074 | E35: =E34*E32 -> 19.1862 | F35: =F34*F32 -> 28.8 | G35: =G34*G32 -> 37.2 | H35: =H34*H32 -> 47.25 | I35: =I34*I32 -> 57.6 | J35: =J34*J32 -> 68.25 | ... O35: =O34*O32 -> 105.6
B36: Driftskostnader | C36: 7.2 | D36: 11.1 | E36: 23.9 | F36: 29 | G36: 34 | H36: 40 | I36: 48 | J36: 52 | K36: 59 | L36: 65 | M36: 71 | N36: 77 | O36: 82
B37: EBITA | C37: =C35-C36 -> -8.1552 | D37: =D35-D36 -> -7.3926 | E37: =E35-E36 -> -4.7138 | F37: =F35-F36 -> -0.2 | G37: =G35-G36 -> 3.2 | H37: =H35-H36 -> 7.25 | I37: =I35-I36 -> 9.6 | J37: =J35-J36 -> 16.25 | ... O37: =O35-O36 -> 23.6
B38: EBITA-margin | C38: =C37/C32 -> -10.194 | D38: =D37/D32 -> -0.999 | E38: =E37/E32 -> -0.14593808 | F38: =F37/F32 -> -0.0041666667 | G38: =G37/G32 -> 0.053333333 | H38: =H37/H32 -> 0.096666667 | I38: =I37/I32 -> 0.10666667 | J38: =J37/J32 -> 0.1547619 | ... O38: =O37/O32 -> 0.1475
B40: KONSERNFUNKSJONER | C40: -14.7 | D40: -22.7 | E40: -17 | F40: =(C40+D40+E40)/3 -> -18.133333 | G40: -18.7 | H40: -19.3 | I40: -19.9 | J40: -20.5 | K40: -21.5 | L40: =-22.5 -> -22.5 | M40: -23.5 | N40: -24.5 | O40: -25.5
B41: EBITA | C41: =C10+C19+C28+C37+C40 -> 161.6768 | D41: =D10+D19+D28+D37+D40 -> 181.5071 | E41: =E10+E19+E28+E37+E40 -> 171.6881 | F41: =F10+F19+F28+F37+F40 -> 192.63637 | G41: =G10+G19+G28+G37+G40 -> 240.88533 | H41: =H10+H19+H28+H37+H40 -> 281.3434 | I41: =I10+I19+I28+I37+I40 -> 313.04177 | J41: =J10+J19+J28+J37+J40 -> 347.84172 | ... O41: =O10+O19+O28+O37+O40 -> 439.80032
B43: TOMRA GROUP
B44: Omsetning | C44: =C32+C23+C14+C5 -> 1287.9 | D44: =D32+D23+D14+D5 -> 1357.2 | E44: =E32+E23+E14+E5 -> 1319 | F44: =F32+F23+F14+F5 -> 1480.04 | G44: =G32+G23+G14+G5 -> 1603.0936 | H44: =H32+H23+H14+H5 -> 1732.8263 | I44: =I32+I23+I14+I5 -> 1854.2302 | J44: =J32+J23+J14+J5 -> 1977.7436 | ... O44: =O32+O23+O14+O5 -> 2486.0392
B45: Vekst | D45: =(D44-C44)/C44 -> 0.053808526 | E45: =(E44-D44)/D44 -> -0.028146183 | F45: =(F44-E44)/E44 -> 0.12209249 | G45: =(G44-F44)/F44 -> 0.083142077 | H45: =(H44-G44)/G44 -> 0.080926496 | I45: =(I44-H44)/H44 -> 0.070061182 | J45: =(J44-I44)/I44 -> 0.0666117 | K45: =(K44-J44)/J44 -> 0.058079762 | ... O45: =(O44-N44)/N44 -> 0.034702905
B46: Bruttobidrag | C46: =C35+C26+C17+C8 -> 548.3768 | D46: =D35+D26+D17+D8 -> 590.5071 | E46: =E35+E26+E17+E8 -> 585.8881 | F46: =F35+F26+F17+F8 -> 630.1647 | G46: =G35+G26+G17+G8 -> 698.08085 | H46: =H35+H26+H17+H8 -> 763.38643 | I46: =I35+I26+I17+I8 -> 822.76559 | J46: =J35+J26+J17+J8 -> 882.11812 | ... O46: =O35+O26+O17+O8 -> 1116.0898
B47: Bruttomargin | C47: =C46/C44 -> 0.42579144 | D47: =D46/D44 -> 0.43509218 | E47: =E46/E44 -> 0.44419113 | F47: =F46/F44 -> 0.42577545 | G47: =G46/G44 -> 0.43545857 | H47: =H46/H44 -> 0.4405441 | I47: =I46/I44 -> 0.44372354 | J47: =J46/J44 -> 0.44602248 | ... O47: =O46/O44 -> 0.44894297
B48: Justert EBITA | C48: =C41 -> 161.6768 | D48: =D41 -> 181.5071 | E48: =E41 -> 171.6881 | F48: =F41 -> 192.63637 | G48: =G41 -> 240.88533 | H48: =H41 -> 281.3434 | I48: =I41 -> 313.04177 | J48: =J41 -> 347.84172 | ... O48: =O41 -> 439.80032
B49: Justert EBITA-margin | C49: =C48/C44 -> 0.12553521 | D49: =D48/D44 -> 0.13373644 | E49: =E48/E44 -> 0.13016535 | F49: =F48/F44 -> 0.13015619 | G49: =G48/G44 -> 0.1502628 | H49: =H48/H44 -> 0.16236099 | I49: =I48/I44 -> 0.16882573 | J49: =J48/J44 -> 0.17587806 | ... O49: =O48/O44 -> 0.17690804
B51: EUR mill | C51: =F4 -> 2026E | D51: =G4 -> 2027E | E51: =H4 -> 2028E | F51: =I4 -> 2029E | G51: =J4 -> 2030E | H51: =K4 -> 2031E | I51: =L4 -> 2032E | J51: =M4 -> 2033E | ... L51: =O4 -> 2035E
B52: Omsetning | C52: =F44 -> 1480.04 | D52: =G44 -> 1603.0936 | E52: =H44 -> 1732.8263 | F52: =I44 -> 1854.2302 | G52: =J44 -> 1977.7436 | H52: =K44 -> 2092.6105 | I52: =L44 -> 2203.341 | J52: =M44 -> 2307.6414 | ... L52: =O44 -> 2486.0392
B53: Justert EBITA | C53: =F48 -> 192.63637 | D53: =G48 -> 240.88533 | E53: =H48 -> 281.3434 | F53: =I48 -> 313.04177 | G53: =J48 -> 347.84172 | H53: =K48 -> 372.26383 | I53: =L48 -> 394.86064 | J53: =M48 -> 414.1687 | ... L53: =O48 -> 439.80032
B54: EBITA-margin | C54: =F49 -> 0.13015619 | D54: =G49 -> 0.1502628 | E54: =H49 -> 0.16236099 | F54: =I49 -> 0.16882573 | G54: =J49 -> 0.17587806 | H54: =K49 -> 0.17789446 | I54: =L49 -> 0.17920995 | J54: =M49 -> 0.17947706 | ... L54: =O49 -> 0.17690804
B55: Amortisering av immatrielle eiendeler | C55: =C52*Antagelser!C19 -> 29.6008 | D55: =D52*Antagelser!D19 -> 30.458778 | E55: =E52*Antagelser!E19 -> 31.190874 | F55: =F52*Antagelser!F19 -> 31.521914 | G55: =G52*Antagelser!G19 -> 33.621642 | H55: =H52*Antagelser!H19 -> 33.481768 | I55: =I52*Antagelser!I19 -> 33.050116 | J55: =J52*Antagelser!J19 -> 32.306979 | ... L55: =L52*Antagelser!L19 -> 29.83247
B56: Justert EBIT | C56: =C53-C55 -> 163.03557 | D56: =D53-D55 -> 210.42656 | E56: =E53-E55 -> 250.15253 | F56: =F53-F55 -> 281.51985 | G56: =G53-G55 -> 314.22008 | H56: =H53-H55 -> 338.78206 | I56: =I53-I55 -> 361.81053 | J56: =J53-J55 -> 381.86172 | ... L56: =L53-L55 -> 409.96785
B57: Skattesats | C57: =Antagelser!C20 -> 0.245 | D57: =Antagelser!D20 -> 0.245 | E57: =Antagelser!E20 -> 0.245 | F57: =Antagelser!F20 -> 0.245 | G57: =Antagelser!G20 -> 0.245 | H57: =Antagelser!H20 -> 0.245 | I57: =Antagelser!I20 -> 0.245 | J57: =Antagelser!J20 -> 0.245 | ... L57: =Antagelser!L20 -> 0.245
B58: NOPAT | C58: =C56*(1-C57) -> 123.09185 | D58: =D56*(1-D57) -> 158.87205 | E58: =E56*(1-E57) -> 188.86516 | F58: =F56*(1-F57) -> 212.54749 | G58: =G56*(1-G57) -> 237.23616 | H58: =H56*(1-H57) -> 255.78045 | I58: =I56*(1-I57) -> 273.16695 | J58: =J56*(1-J57) -> 288.3056 | ... L58: =L56*(1-L57) -> 309.52573
B59: Avskrivninger og amortisering | C59: =C52*Antagelser!C21 -> 125.8034 | D59: =D52*Antagelser!D21 -> 133.05677 | E59: =E52*Antagelser!E21 -> 138.62611 | F59: =F52*Antagelser!F21 -> 144.62996 | G59: =G52*Antagelser!G21 -> 148.33077 | H59: =H52*Antagelser!H21 -> 152.76057 | I59: =I52*Antagelser!I21 -> 156.43721 | J59: =J52*Antagelser!J21 -> 159.22726 | ... L59: =L52*Antagelser!L21 -> 161.59255
B60: Capex | C60: =C52*Antagelser!C22 -> 148.004 | D60: =D52*Antagelser!D22 -> 152.29389 | E60: =E52*Antagelser!E22 -> 155.95437 | F60: =F52*Antagelser!F22 -> 157.60957 | G60: =G52*Antagelser!G22 -> 158.21949 | H60: =H52*Antagelser!H22 -> 163.22362 | I60: =I52*Antagelser!I22 -> 171.8606 | J60: =J52*Antagelser!J22 -> 179.99603 | ... L60: =L52*Antagelser!L22 -> 193.91106
B61: Arbeidskapital | C61: =C52*Antagelser!C23 -> 370.01 | D61: =D52*Antagelser!D23 -> 392.75793 | E61: =E52*Antagelser!E23 -> 415.87832 | F61: =F52*Antagelser!F23 -> 435.7441 | G61: =G52*Antagelser!G23 -> 454.88104 | H61: =H52*Antagelser!H23 -> 481.30042 | I61: =I52*Antagelser!I23 -> 502.36176 | J61: =J52*Antagelser!J23 -> 521.52695 | ... L61: =L52*Antagelser!L23 -> 559.35882
B62: Endring i arbeidskapital | C62: =C61-'Historiske finansielle tall'!J35 -> 41.31 | D62: =D61-C61 -> 22.747932 | E62: =E61-D61 -> 23.120392 | F62: =F61-E61 -> 19.865776 | G62: =G61-F61 -> 19.136937 | H62: =H61-G61 -> 26.419382 | I62: =I61-H61 -> 21.061339 | J62: =J61-I61 -> 19.165196 | K62: =K61-J61 -> 19.071525 | L62: =L61-K61 -> 18.760338
B63: FCFF | C63: =C58+C59-C60-C62 -> 59.581253 | D63: =D58+D59-D60-D62 -> 116.88699 | E63: =E58+E59-E60-E62 -> 148.4165 | F63: =F58+F59-F60-F62 -> 179.7021 | G63: =G58+G59-G60-G62 -> 208.2105 | H63: =H58+H59-H60-H62 -> 218.89802 | I63: =I58+I59-I60-I62 -> 236.68222 | J63: =J58+J59-J60-J62 -> 248.37163 | ... L63: =L58+L59-L60-L62 -> 258.44688
B64: FCFF-margin | C64: =C63/C52 -> 0.040256515 | D64: =D63/D52 -> 0.072913393 | E64: =E63/E52 -> 0.085649957 | F64: =F63/F52 -> 0.096914666 | G64: =G63/G52 -> 0.10527679 | H64: =H63/H52 -> 0.10460524 | I64: =I63/I52 -> 0.10741969 | J64: =J63/J52 -> 0.10763008 | ... L64: =L63/L52 -> 0.1039593

Sheet Forecast Bear
B2: Forecast Bear
B4: COLLECTION | C4: 2023 | D4: 2024 | E4: 2025 | F4: 2026E | G4: 2027E | H4: 2028E | I4: 2029E | J4: 2030E | K4: 2031E | L4: 2032E | M4: 2033E | N4: 2034E | O4: 2035E
B5: Omsetning | C5: 697.4 | D5: 773.1 | E5: 740.5 | F5: =E5*(1+Antagelser!C30) -> 858.98 | G5: =F5*(1+Antagelser!D30) -> 919.1086 | H5: =G5*(1+Antagelser!E30) -> 974.25512 | I5: =H5*(1+Antagelser!F30) -> 1022.9679 | J5: =I5*(1+Antagelser!G30) -> 1074.1163 | K5: =J5*(1+Antagelser!H30) -> 1122.4515 | L5: =K5*(1+Antagelser!I30) -> 1167.3496 | M5: =L5*(1+Antagelser!J30) -> 1208.2068 | ... O5: =N5*(1+Antagelser!L30) -> 1275.5643
B6: Vekst | D6: =(D5-C5)/C5 -> 0.10854603 | E6: =(E5-D5)/D5 -> -0.042167895 | F6: =(F5-E5)/E5 -> 0.16 | G6: =(G5-F5)/F5 -> 0.07 | H6: =(H5-G5)/G5 -> 0.06 | I6: =(I5-H5)/H5 -> 0.05 | J6: =(J5-I5)/I5 -> 0.05 | K6: =(K5-J5)/J5 -> 0.045 | ... O6: =(O5-N5)/N5 -> 0.025
B7: Bruttomargin | C7: 0.399 | D7: 0.406 | E7: 0.417 | F7: =Antagelser!C31 -> 0.395 | G7: =Antagelser!D31 -> 0.4 | H7: =Antagelser!E31 -> 0.4 | I7: =Antagelser!F31 -> 0.402 | J7: =Antagelser!G31 -> 0.402 | K7: =Antagelser!H31 -> 0.402 | L7: =Antagelser!I31 -> 0.404 | M7: =Antagelser!J31 -> 0.405 | ... O7: =Antagelser!L31 -> 0.405
B8: Bruttobidrag | C8: =C5*C7 -> 278.2626 | D8: =D5*D7 -> 313.8786 | E8: =E5*E7 -> 308.7885 | F8: =F5*F7 -> 339.2971 | G8: =G5*G7 -> 367.64344 | H8: =H5*H7 -> 389.70205 | I8: =I5*I7 -> 411.23308 | J8: =J5*J7 -> 431.79474 | ... O8: =O5*O7 -> 516.60355
B9: Driftskostnader | C9: 162.9 | D9: 183.2 | E9: 182.4 | F9: =E9*(1+Antagelser!C32) -> 199.728 | G9: =F9*(1+Antagelser!D32) -> 209.7144 | H9: =G9*(1+Antagelser!E32) -> 220.20012 | I9: =H9*(1+Antagelser!F32) -> 232.31113 | J9: =I9*(1+Antagelser!G32) -> 245.08824 | K9: =J9*(1+Antagelser!H32) -> 256.11721 | L9: =K9*(1+Antagelser!I32) -> 266.87413 | M9: =L9*(1+Antagelser!J32) -> 277.5491 | ... O9: =N9*(1+Antagelser!L32) -> 298.17932
B10: Justert EBITA | C10: =C8-C9 -> 115.3626 | D10: =D8-D9 -> 130.6786 | E10: =E8-E9 -> 126.3885 | F10: =F8-F9 -> 139.5691 | G10: =G8-G9 -> 157.92904 | H10: =H8-H9 -> 169.50193 | I10: =I8-I9 -> 178.92196 | J10: =J8-J9 -> 186.7065 | ... O10: =O8-O9 -> 218.42423
B11: Justert EBITA-margin | C11: =C10/C5 -> 0.16541812 | D11: =D10/D5 -> 0.16903195 | E11: =E10/E5 -> 0.17067995 | F11: =F10/F5 -> 0.16248236 | G11: =G10/G5 -> 0.17182849 | H11: =H10/H5 -> 0.17398105 | I11: =I10/I5 -> 0.17490477 | J11: =J10/J5 -> 0.17382336 | ... O11: =O10/O5 -> 0.17123733
B13: RECYCLING
B14: Omsetning | C14: 270.1 | D14: 265.8 | E14: 218.2 | F14: =E14*(1+Antagelser!C35) -> 200.744 | G14: =F14*(1+Antagelser!D35) -> 210.7812 | H14: =G14*(1+Antagelser!E35) -> 227.6437 | I14: =H14*(1+Antagelser!F35) -> 243.57875 | J14: =I14*(1+Antagelser!G35) -> 260.62927 | K14: =J14*(1+Antagelser!H35) -> 272.35758 | L14: =K14*(1+Antagelser!I35) -> 284.61368 | M14: =L14*(1+Antagelser!J35) -> 295.99822 | ... O14: =N14*(1+Antagelser!L35) -> 315.54891
B15: Vekst | D15: =(D14-C14)/C14 -> -0.01592003 | E15: =(E14-D14)/D14 -> -0.17908202 | F15: =(F14-E14)/E14 -> -0.08 | G15: =(G14-F14)/F14 -> 0.05 | H15: =(H14-G14)/G14 -> 0.08 | I15: =(I14-H14)/H14 -> 0.07 | J15: =(J14-I14)/I14 -> 0.07 | K15: =(K14-J14)/J14 -> 0.045 | ... O15: =(O14-N14)/N14 -> 0.03
B16: Bruttomargin | C16: 0.522 | D16: 0.525 | E16: 0.477 | F16: =Antagelser!C36 -> 0.45 | G16: =Antagelser!D36 -> 0.47 | H16: =Antagelser!E36 -> 0.485 | I16: =Antagelser!F36 -> 0.495 | J16: =Antagelser!G36 -> 0.5 | K16: =Antagelser!H36 -> 0.505 | L16: =Antagelser!I36 -> 0.51 | M16: =Antagelser!J36 -> 0.513 | ... O16: =Antagelser!L36 -> 0.515
B17: Bruttobidrag | C17: =C16*C14 -> 140.9922 | D17: =D16*D14 -> 139.545 | E17: =E16*E14 -> 104.0814 | F17: =F16*F14 -> 90.3348 | G17: =G16*G14 -> 99.067164 | H17: =H16*H14 -> 110.40719 | I17: =I16*I14 -> 120.57148 | J17: =J16*J14 -> 130.31463 | ... O17: =O16*O14 -> 162.50769
B18: Driftskostnader | C18: 79.5 | D18: 79.4 | E18: 80.6 | F18: =E18*(1+Antagelser!C37) -> 76.57 | G18: =F18*(1+Antagelser!D37) -> 78.8671 | H18: =G18*(1+Antagelser!E37) -> 82.810455 | I18: =H18*(1+Antagelser!F37) -> 86.950978 | J18: =I18*(1+Antagelser!G37) -> 91.298527 | K18: =J18*(1+Antagelser!H37) -> 94.037482 | L18: =K18*(1+Antagelser!I37) -> 97.046682 | M18: =L18*(1+Antagelser!J37) -> 100.15218 | ... O18: =N18*(1+Antagelser!L37) -> 106.04513
B19: Justert EBITA | C19: =C17-C18 -> 61.4922 | D19: =D17-D18 -> 60.145 | E19: =E17-E18 -> 23.4814 | F19: =F17-F18 -> 13.7648 | G19: =G17-G18 -> 20.200064 | H19: =H17-H18 -> 27.596738 | I19: =I17-I18 -> 33.620506 | J19: =J17-J18 -> 39.016107 | ... O19: =O17-O18 -> 56.462557
B20: Justert EBITA-margin | C20: =C19/C14 -> 0.22766457 | D20: =D19/D14 -> 0.22627916 | E20: =E19/E14 -> 0.10761412 | F20: =F19/F14 -> 0.068568924 | G20: =G19/G14 -> 0.095834277 | H20: =H19/H14 -> 0.12122777 | I20: =I19/I14 -> 0.13802725 | J20: =J19/J14 -> 0.14969964 | ... O20: =O19/O14 -> 0.17893441
B22: FOOD
B23: Omsetning | C23: 319.6 | D23: 310.9 | E23: 328 | F23: =E23*(1+Antagelser!C40) -> 344.4 | G23: =F23*(1+Antagelser!D40) -> 361.62 | H23: =G23*(1+Antagelser!E40) -> 379.701 | I23: =H23*(1+Antagelser!F40) -> 396.78755 | J23: =I23*(1+Antagelser!G40) -> 412.65905 | K23: =J23*(1+Antagelser!H40) -> 429.16541 | L23: =K23*(1+Antagelser!I40) -> 446.33203 | M23: =L23*(1+Antagelser!J40) -> 461.95365 | ... O23: =N23*(1+Antagelser!L40) -> 487.70756
B24: Vekst | D24: =(D23-C23)/C23 -> -0.027221527 | E24: =(E23-D23)/D23 -> 0.055001608 | F24: =(F23-E23)/E23 -> 0.05 | G24: =(G23-F23)/F23 -> 0.05 | H24: =(H23-G23)/G23 -> 0.05 | I24: =(I23-H23)/H23 -> 0.045 | J24: =(J23-I23)/I23 -> 0.04 | K24: =(K23-J23)/J23 -> 0.04 | ... O24: =(O23-N23)/N23 -> 0.025
B25: Bruttomargin | C25: 0.407 | D25: 0.429 | E25: 0.469 | F25: =Antagelser!C41 -> 0.425 | G25: =Antagelser!D41 -> 0.435 | H25: =Antagelser!E41 -> 0.435 | I25: =Antagelser!F41 -> 0.44 | J25: =Antagelser!G41 -> 0.445 | K25: =Antagelser!H41 -> 0.448 | L25: =Antagelser!I41 -> 0.45 | M25: =Antagelser!J41 -> 0.452 | ... O25: =Antagelser!L41 -> 0.455
B26: Bruttobidrag | C26: =C23*C25 -> 130.0772 | D26: =D23*D25 -> 133.3761 | E26: =E23*E25 -> 153.832 | F26: =F23*F25 -> 146.37 | G26: =G23*G25 -> 157.3047 | H26: =H23*H25 -> 165.16994 | I26: =I23*I25 -> 174.58652 | J26: =J23*J25 -> 183.63328 | ... O26: =O23*O25 -> 221.90694
B27: Driftskostnader | C27: 122.4 | D27: 112.6 | E27: 110.3 | F27: =E27*(1+Antagelser!C42) -> 116.918 | G27: =F27*(1+Antagelser!D42) -> 122.7639 | H27: =G27*(1+Antagelser!E42) -> 128.9021 | I27: =H27*(1+Antagelser!F42) -> 135.3472 | J27: =I27*(1+Antagelser!G42) -> 142.11456 | K27: =J27*(1+Antagelser!H42) -> 147.08857 | L27: =K27*(1+Antagelser!I42) -> 152.23667 | M27: =L27*(1+Antagelser!J42) -> 157.26048 | ... O27: =N27*(1+Antagelser!L42) -> 166.51369
B28: Justert EBITA | C28: =C26-C27 -> 7.6772 | D28: =D26-D27 -> 20.7761 | E28: =E26-E27 -> 43.532 | F28: =F26-F27 -> 29.452 | G28: =G26-G27 -> 34.5408 | H28: =H26-H27 -> 36.26784 | I28: =I26-I27 -> 39.23932 | J28: =J26-J27 -> 41.518716 | ... O28: =O26-O27 -> 55.393255
B29: Justert EBITA-margin | C29: =C28/C23 -> 0.024021277 | D29: =D28/D23 -> 0.066825667 | E29: =E28/E23 -> 0.13271951 | F29: =F28/F23 -> 0.085516841 | G29: =G28/G23 -> 0.095516841 | H29: =H28/H23 -> 0.095516841 | I29: =I28/I23 -> 0.09889252 | J29: =J28/J23 -> 0.10061264 | ... O29: =O28/O23 -> 0.11357883
B31: HORIZON
B32: Omsetning | C32: 0.8 | D32: 7.4 | E32: 32.3 | F32: 48 | G32: =60*0.85 -> 51 | H32: =75*0.85 -> 63.75 | I32: =90*0.85 -> 76.5 | J32: =105*0.85 -> 89.25 | K32: ='Forecast Base'!K32*0.85 -> 100.3 | L32: ='Forecast Base'!L32*0.85 -> 110.5 | M32: ='Forecast Base'!M32*0.85 -> 119.85 | N32: ='Forecast Base'!N32*0.85 -> 128.35 | O32: ='Forecast Base'!O32*0.85 -> 136
B33: Vekst | D33: =(D32-C32)/C32 -> 8.25 | E33: =(E32-D32)/D32 -> 3.3648649 | F33: =(F32-E32)/E32 -> 0.48606811 | G33: =(G32-F32)/F32 -> 0.0625 | H33: =(H32-G32)/G32 -> 0.25 | I33: =(I32-H32)/H32 -> 0.2 | J33: =(J32-I32)/I32 -> 0.16666667 | K33: =(K32-J32)/J32 -> 0.12380952 | ... O33: =(O32-N32)/N32 -> 0.059602649
B34: Bruttomargin | C34: -1.194 | D34: 0.501 | E34: 0.594 | F34: 0.6 | G34: 0.6 | H34: 0.6 | I34: 0.6 | J34: 0.6 | K34: 0.6 | L34: 0.6 | M34: 0.6 | N34: 0.6 | O34: 0.6
B35: Bruttobidrag | C35: =C34*C32 -> -0.9552 | D35: =D34*D32 -> 3.7074 | E35: =E34*E32 -> 19.1862 | F35: =F34*F32 -> 28.8 | G35: =G34*G32 -> 30.6 | H35: =H34*H32 -> 38.25 | I35: =I34*I32 -> 45.9 | J35: =J34*J32 -> 53.55 | ... O35: =O34*O32 -> 81.6
B36: Driftskostnader | C36: 7.2 | D36: 11.1 | E36: 23.9 | F36: 29 | G36: =34*0.95 -> 32.3 | H36: =40*0.95 -> 38 | I36: =48*0.95 -> 45.6 | J36: =52*0.95 -> 49.4 | K36: ='Forecast Base'!K36*0.95 -> 56.05 | L36: ='Forecast Base'!L36*0.95 -> 61.75 | M36: ='Forecast Base'!M36*0.95 -> 67.45 | N36: ='Forecast Base'!N36*0.95 -> 73.15 | O36: ='Forecast Base'!O36*0.95 -> 77.9
B37: EBITA | C37: =C35-C36 -> -8.1552 | D37: =D35-D36 -> -7.3926 | E37: =E35-E36 -> -4.7138 | F37: =F35-F36 -> -0.2 | G37: =G35-G36 -> -1.7 | H37: =H35-H36 -> 0.25 | I37: =I35-I36 -> 0.3 | J37: =J35-J36 -> 4.15 | ... O37: =O35-O36 -> 3.7
B38: EBITA-margin | C38: =C37/C32 -> -10.194 | D38: =D37/D32 -> -0.999 | E38: =E37/E32 -> -0.14593808 | F38: =F37/F32 -> -0.0041666667 | G38: =G37/G32 -> -0.033333333 | H38: =H37/H32 -> 0.0039215686 | I38: =I37/I32 -> 0.0039215686 | J38: =J37/J32 -> 0.046498599 | ... O38: =O37/O32 -> 0.027205882
B40: KONSERNFUNKSJONER | C40: -14.7 | D40: -22.7 | E40: -17 | F40: =(C40+D40+E40)/3 -> -18.133333 | G40: -18.7 | H40: -19.3 | I40: -19.9 | J40: -20.5 | K40: ='Forecast Base'!K40 -> -21.5 | L40: ='Forecast Base'!L40 -> -22.5 | M40: ='Forecast Base'!M40 -> -23.5 | N40: ='Forecast Base'!N40 -> -24.5 | O40: ='Forecast Base'!O40 -> -25.5
B41: EBITA | C41: =C10+C19+C28+C37+C40 -> 161.6768 | D41: =D10+D19+D28+D37+D40 -> 181.5071 | E41: =E10+E19+E28+E37+E40 -> 171.6881 | F41: =F10+F19+F28+F37+F40 -> 164.45257 | G41: =G10+G19+G28+G37+G40 -> 192.2699 | H41: =H10+H19+H28+H37+H40 -> 214.3165 | I41: =I10+I19+I28+I37+I40 -> 232.18178 | J41: =J10+J19+J28+J37+J40 -> 250.89132 | ... O41: =O10+O19+O28+O37+O40 -> 308.48004
B43: TOMRA GROUP
B44: Omsetning | C44: =C32+C23+C14+C5 -> 1287.9 | D44: =D32+D23+D14+D5 -> 1357.2 | E44: =E32+E23+E14+E5 -> 1319 | F44: =F32+F23+F14+F5 -> 1452.124 | G44: =G32+G23+G14+G5 -> 1542.5098 | H44: =H32+H23+H14+H5 -> 1645.3498 | I44: =I32+I23+I14+I5 -> 1739.8342 | J44: =J32+J23+J14+J5 -> 1836.6546 | ... O44: =O32+O23+O14+O5 -> 2214.8208
B45: Vekst | D45: =(D44-C44)/C44 -> 0.053808526 | E45: =(E44-D44)/D44 -> -0.028146183 | F45: =(F44-E44)/E44 -> 0.10092798 | G45: =(G44-F44)/F44 -> 0.062243858 | H45: =(H44-G44)/G44 -> 0.066670573 | I45: =(I44-H44)/H44 -> 0.057425089 | J45: =(J44-I44)/I44 -> 0.055649216 | K45: =(K44-J44)/J44 -> 0.047706255 | ... O45: =(O44-N44)/N44 -> 0.027771747
B46: Bruttobidrag | C46: =C35+C26+C17+C8 -> 548.3768 | D46: =D35+D26+D17+D8 -> 590.5071 | E46: =E35+E26+E17+E8 -> 585.8881 | F46: =F35+F26+F17+F8 -> 604.8019 | G46: =G35+G26+G17+G8 -> 654.6153 | H46: =H35+H26+H17+H8 -> 703.52917 | I46: =I35+I26+I17+I8 -> 752.29109 | J46: =J35+J26+J17+J8 -> 799.29265 | ... O46: =O35+O26+O17+O8 -> 982.61818
B47: Bruttomargin | C47: =C46/C44 -> 0.42579144 | D47: =D46/D44 -> 0.43509218 | E47: =E46/E44 -> 0.44419113 | F47: =F46/F44 -> 0.41649467 | G47: =G46/G44 -> 0.42438324 | H47: =H46/H44 -> 0.42758638 | I47: =I46/I44 -> 0.43239241 | J47: =J46/J44 -> 0.43518942 | ... O47: =O46/O44 -> 0.44365584
B48: Justert EBITA | C48: =C41 -> 161.6768 | D48: =D41 -> 181.5071 | E48: =E41 -> 171.6881 | F48: =F41 -> 164.45257 | G48: =G41 -> 192.2699 | H48: =H41 -> 214.3165 | I48: =I41 -> 232.18178 | J48: =J41 -> 250.89132 | ... O48: =O41 -> 308.48004
B49: Justert EBITA-margin | C49: =C48/C44 -> 0.12553521 | D49: =D48/D44 -> 0.13373644 | E49: =E48/E44 -> 0.13016535 | F49: =F48/F44 -> 0.11324967 | G49: =G48/G44 -> 0.12464744 | H49: =H48/H44 -> 0.13025589 | I49: =I48/I44 -> 0.13345053 | J49: =J48/J44 -> 0.13660235 | ... O49: =O48/O44 -> 0.13927991
B51: EUR mill | C51: =F4 -> 2026E | D51: =G4 -> 2027E | E51: =H4 -> 2028E | F51: =I4 -> 2029E | G51: =J4 -> 2030E | H51: =K4 -> 2031E | I51: =L4 -> 2032E | J51: =M4 -> 2033E | ... L51: =O4 -> 2035E
B52: Omsetning | C52: =F44 -> 1452.124 | D52: =G44 -> 1542.5098 | E52: =H44 -> 1645.3498 | F52: =I44 -> 1739.8342 | G52: =J44 -> 1836.6546 | H52: =K44 -> 1924.2745 | I52: =L44 -> 2008.7953 | J52: =M44 -> 2086.0087 | ... L52: =O44 -> 2214.8208
B53: Justert EBITA | C53: =F48 -> 164.45257 | D53: =G48 -> 192.2699 | E53: =H48 -> 214.3165 | F53: =I48 -> 232.18178 | G53: =J48 -> 250.89132 | H53: =K48 -> 266.41892 | I53: =L48 -> 283.50412 | J53: =M48 -> 295.97213 | ... L53: =O48 -> 308.48004
B54: EBITA-margin | C54: =F49 -> 0.11324967 | D54: =G49 -> 0.12464744 | E54: =H49 -> 0.13025589 | F54: =I49 -> 0.13345053 | G54: =J49 -> 0.13660235 | H54: =K49 -> 0.13845162 | I54: =L49 -> 0.14113142 | J54: =M49 -> 0.14188442 | ... L54: =O49 -> 0.13927991
B55: Amortisering av immatrielle eiendeler | C55: =Antagelser!C45*C52 -> 29.04248 | D55: =Antagelser!D45*D52 -> 29.307686 | E55: =Antagelser!E45*E52 -> 29.616297 | F55: =Antagelser!F45*F52 -> 29.577181 | G55: =Antagelser!G45*G52 -> 31.223128 | H55: =Antagelser!H45*H52 -> 30.788392 | I55: =Antagelser!I45*I52 -> 30.131929 | J55: =Antagelser!J45*J52 -> 29.204121 | ... L55: =Antagelser!L45*L52 -> 26.577849
B56: Justert EBIT | C56: =C53-C55 -> 135.41009 | D56: =D53-D55 -> 162.96222 | E56: =E53-E55 -> 184.70021 | F56: =F53-F55 -> 202.6046 | G56: =G53-G55 -> 219.6682 | H56: =H53-H55 -> 235.63053 | I56: =I53-I55 -> 253.37219 | J56: =J53-J55 -> 266.76801 | ... L56: =L53-L55 -> 281.90219
B57: Skattesats | C57: =Antagelser!C46 -> 0.25 | D57: =Antagelser!D46 -> 0.25 | E57: =Antagelser!E46 -> 0.25 | F57: =Antagelser!F46 -> 0.25 | G57: =Antagelser!G46 -> 0.25 | H57: =Antagelser!H46 -> 0.25 | I57: =Antagelser!I46 -> 0.25 | J57: =Antagelser!J46 -> 0.25 | ... L57: =Antagelser!L46 -> 0.25
B58: NOPAT | C58: =C56*(1-C57) -> 101.55756 | D58: =D56*(1-D57) -> 122.22166 | E58: =E56*(1-E57) -> 138.52516 | F58: =F56*(1-F57) -> 151.95345 | G58: =G56*(1-G57) -> 164.75115 | H58: =H56*(1-H57) -> 176.7229 | I58: =I56*(1-I57) -> 190.02915 | J58: =J56*(1-J57) -> 200.07601 | ... L58: =L56*(1-L57) -> 211.42664
B59: Avskrivninger og amortisering | C59: =C52*Antagelser!C47 -> 123.43054 | D59: =D52*Antagelser!D47 -> 128.02831 | E59: =E52*Antagelser!E47 -> 131.62798 | F59: =F52*Antagelser!F47 -> 135.70707 | G59: =G52*Antagelser!G47 -> 137.74909 | H59: =H52*Antagelser!H47 -> 140.47204 | I59: =I52*Antagelser!I47 -> 142.62446 | J59: =J52*Antagelser!J47 -> 143.9346 | ... L59: =L52*Antagelser!L47 -> 143.96335
B60: Capex | C60: =C52*Antagelser!C48 -> 152.47302 | D60: =D52*Antagelser!D48 -> 154.25098 | E60: =E52*Antagelser!E48 -> 156.30823 | F60: =F52*Antagelser!F48 -> 156.58508 | G60: =G52*Antagelser!G48 -> 156.11564 | H60: =H52*Antagelser!H48 -> 169.33616 | I60: =I52*Antagelser!I48 -> 172.75639 | J60: =J52*Antagelser!J48 -> 175.22473 | ... L60: =L52*Antagelser!L48 -> 177.18566
B61: Arbeidskapital | C61: =C52*Antagelser!C49 -> 370.29162 | D61: =D52*Antagelser!D49 -> 385.62745 | E61: =E52*Antagelser!E49 -> 403.1107 | F61: =F52*Antagelser!F49 -> 417.5602 | G61: =G52*Antagelser!G49 -> 431.61383 | H61: =H52*Antagelser!H49 -> 452.20451 | I61: =I52*Antagelser!I49 -> 468.0493 | J61: =J52*Antagelser!J49 -> 479.78199 | ... L61: =L52*Antagelser!L49 -> 498.33468
B62: Endring i arbeidskapital | C62: =C61-'Historiske finansielle tall'!J35 -> 41.59162 | D62: =D61-C61 -> 15.33583 | E62: =E61-D61 -> 17.483254 | F62: =F61-E61 -> 14.449497 | G62: =G61-F61 -> 14.053625 | H62: =H61-G61 -> 20.590679 | I62: =I61-H61 -> 15.84479 | J62: =J61-I61 -> 11.732697 | K62: =K61-J61 -> 11.551946 | L62: =L61-K61 -> 7.0007394
B63: FCFF | C63: =C58+C59-C60-C62 -> 30.923465 | D63: =D58+D59-D60-D62 -> 80.663167 | E63: =E58+E59-E60-E62 -> 96.361654 | F63: =F58+F59-F60-F62 -> 116.62594 | G63: =G58+G59-G60-G62 -> 132.33098 | H63: =H58+H59-H60-H62 -> 127.2681 | I63: =I58+I59-I60-I62 -> 144.05243 | J63: =J58+J59-J60-J62 -> 157.05318 | ... L63: =L58+L59-L60-L62 -> 171.20359
B64: FCFF-margin | C64: =C63/C52 -> 0.021295334 | D64: =D63/D52 -> 0.052293455 | E64: =E63/E52 -> 0.058566059 | F64: =F63/F52 -> 0.067032794 | G64: =G63/G52 -> 0.072050007 | H64: =H63/H52 -> 0.066138227 | I64: =I63/I52 -> 0.071710856 | J64: =J63/J52 -> 0.075288845 | ... L64: =L63/L52 -> 0.077299072

Sheet Forecast Bull
B2: Forecast Bull
B4: COLLECTION | C4: 2023 | D4: 2024 | E4: 2025 | F4: 2026E | G4: 2027E | H4: 2028E | I4: 2029E | J4: 2030E | K4: 2031E | L4: 2032E | M4: 2033E | N4: 2034E | O4: 2035E
B5: Omsetning | C5: 697.4 | D5: 773.1 | E5: 740.5 | F5: =E5*(1+Antagelser!C56) -> 881.195 | G5: =F5*(1+Antagelser!D56) -> 960.50255 | H5: =G5*(1+Antagelser!E56) -> 1046.9478 | I5: =H5*(1+Antagelser!F56) -> 1135.9383 | J5: =I5*(1+Antagelser!G56) -> 1226.8134 | K5: =J5*(1+Antagelser!H56) -> 1306.5563 | L5: =K5*(1+Antagelser!I56) -> 1384.9497 | M5: =L5*(1+Antagelser!J56) -> 1461.1219 | ... O5: =N5*(1+Antagelser!L56) -> 1603.216
B6: Vekst | D6: =(D5-C5)/C5 -> 0.10854603 | E6: =(E5-D5)/D5 -> -0.042167895 | F6: =(F5-E5)/E5 -> 0.19 | G6: =(G5-F5)/F5 -> 0.09 | H6: =(H5-G5)/G5 -> 0.09 | I6: =(I5-H5)/H5 -> 0.085 | J6: =(J5-I5)/I5 -> 0.08 | K6: =(K5-J5)/J5 -> 0.065 | ... O6: =(O5-N5)/N5 -> 0.045
B7: Bruttomargin | C7: 0.399 | D7: 0.406 | E7: 0.417 | F7: =Antagelser!C57 -> 0.41 | G7: =Antagelser!D57 -> 0.415 | H7: =Antagelser!E57 -> 0.415 | I7: =Antagelser!F57 -> 0.418 | J7: =Antagelser!G57 -> 0.418 | K7: =Antagelser!H57 -> 0.418 | L7: =Antagelser!I57 -> 0.418 | M7: =Antagelser!J57 -> 0.418 | ... O7: =Antagelser!L57 -> 0.418
B8: Bruttobidrag | C8: =C5*C7 -> 278.2626 | D8: =D5*D7 -> 313.8786 | E8: =E5*E7 -> 308.7885 | F8: =F5*F7 -> 361.28995 | G8: =G5*G7 -> 398.60856 | H8: =H5*H7 -> 434.48333 | I8: =I5*I7 -> 474.82223 | J8: =J5*J7 -> 512.808 | ... O8: =O5*O7 -> 670.14428
B9: Driftskostnader | C9: 162.9 | D9: 183.2 | E9: 182.4 | F9: =E9*(1+Antagelser!C58) -> 196.992 | G9: =F9*(1+Antagelser!D58) -> 202.90176 | H9: =G9*(1+Antagelser!E58) -> 211.01783 | I9: =H9*(1+Antagelser!F58) -> 219.45854 | J9: =I9*(1+Antagelser!G58) -> 228.23689 | K9: =J9*(1+Antagelser!H58) -> 243.07228 | L9: =K9*(1+Antagelser!I58) -> 257.65662 | M9: =L9*(1+Antagelser!J58) -> 271.82773 | ... O9: =N9*(1+Antagelser!L58) -> 298.26298
B10: Justert EBITA | C10: =C8-C9 -> 115.3626 | D10: =D8-D9 -> 130.6786 | E10: =E8-E9 -> 126.3885 | F10: =F8-F9 -> 164.29795 | G10: =G8-G9 -> 195.7068 | H10: =H8-H9 -> 223.4655 | I10: =I8-I9 -> 255.36368 | J10: =J8-J9 -> 284.57112 | ... O10: =O8-O9 -> 371.8813
B11: Justert EBITA-margin | C11: =C10/C5 -> 0.16541812 | D11: =D10/D5 -> 0.16903195 | E11: =E10/E5 -> 0.17067995 | F11: =F10/F5 -> 0.18644903 | G11: =G10/G5 -> 0.20375458 | H11: =H10/H5 -> 0.21344474 | I11: =I10/I5 -> 0.22480418 | J11: =J10/J5 -> 0.23195958 | ... O11: =O10/O5 -> 0.23195958
B13: RECYCLING
B14: Omsetning | C14: 270.1 | D14: 265.8 | E14: 218.2 | F14: =E14*(1+Antagelser!C61) -> 211.654 | G14: =F14*(1+Antagelser!D61) -> 232.8194 | H14: =G14*(1+Antagelser!E61) -> 260.75773 | I14: =H14*(1+Antagelser!F61) -> 286.8335 | J14: =I14*(1+Antagelser!G61) -> 311.21435 | K14: =J14*(1+Antagelser!H61) -> 331.44328 | L14: =K14*(1+Antagelser!I61) -> 351.32988 | M14: =L14*(1+Antagelser!J61) -> 370.65302 | ... O14: =N14*(1+Antagelser!L61) -> 404.7531
B15: Vekst | D15: =(D14-C14)/C14 -> -0.01592003 | E15: =(E14-D14)/D14 -> -0.17908202 | F15: =(F14-E14)/E14 -> -0.03 | G15: =(G14-F14)/F14 -> 0.1 | H15: =(H14-G14)/G14 -> 0.12 | I15: =(I14-H14)/H14 -> 0.1 | J15: =(J14-I14)/I14 -> 0.085 | K15: =(K14-J14)/J14 -> 0.065 | ... O15: =(O14-N14)/N14 -> 0.04
B16: Bruttomargin | C16: 0.522 | D16: 0.525 | E16: 0.477 | F16: =Antagelser!C62 -> 0.48 | G16: =Antagelser!D62 -> 0.5 | H16: =Antagelser!E62 -> 0.515 | I16: =Antagelser!F62 -> 0.525 | J16: =Antagelser!G62 -> 0.53 | K16: =Antagelser!H62 -> 0.53 | L16: =Antagelser!I62 -> 0.53 | M16: =Antagelser!J62 -> 0.53 | ... O16: =Antagelser!L62 -> 0.53
B17: Bruttobidrag | C17: =C16*C14 -> 140.9922 | D17: =D16*D14 -> 139.545 | E17: =E16*E14 -> 104.0814 | F17: =F16*F14 -> 101.59392 | G17: =G16*G14 -> 116.4097 | H17: =H16*H14 -> 134.29023 | I17: =I16*I14 -> 150.58759 | J17: =J16*J14 -> 164.9436 | ... O17: =O16*O14 -> 214.51914
B18: Driftskostnader | C18: 79.5 | D18: 79.4 | E18: 80.6 | F18: =E18*(1+Antagelser!C63) -> 74.958 | G18: =F18*(1+Antagelser!D63) -> 75.70758 | H18: =G18*(1+Antagelser!E63) -> 77.978807 | I18: =H18*(1+Antagelser!F63) -> 81.09796 | J18: =I18*(1+Antagelser!G63) -> 84.341878 | K18: =J18*(1+Antagelser!H63) -> 89.8241 | L18: =K18*(1+Antagelser!I63) -> 95.213546 | M18: =L18*(1+Antagelser!J63) -> 100.45029 | ... O18: =N18*(1+Antagelser!L63) -> 109.69172
B19: Justert EBITA | C19: =C17-C18 -> 61.4922 | D19: =D17-D18 -> 60.145 | E19: =E17-E18 -> 23.4814 | F19: =F17-F18 -> 26.63592 | G19: =G17-G18 -> 40.70212 | H19: =H17-H18 -> 56.311423 | I19: =I17-I18 -> 69.489628 | J19: =J17-J18 -> 80.601727 | ... O19: =O17-O18 -> 104.82742
B20: Justert EBITA-margin | C20: =C19/C14 -> 0.22766457 | D20: =D19/D14 -> 0.22627916 | E20: =E19/E14 -> 0.10761412 | F20: =F19/F14 -> 0.12584652 | G20: =G19/G14 -> 0.17482272 | H20: =H19/H14 -> 0.21595303 | I20: =I19/I14 -> 0.24226469 | J20: =J19/J14 -> 0.25899104 | ... O20: =O19/O14 -> 0.25899104
B22: FOOD
B23: Omsetning | C23: 319.6 | D23: 310.9 | E23: 328 | F23: =E23*(1+Antagelser!C66) -> 352.6 | G23: =F23*(1+Antagelser!D66) -> 380.808 | H23: =G23*(1+Antagelser!E66) -> 411.27264 | I23: =H23*(1+Antagelser!F66) -> 444.17445 | J23: =I23*(1+Antagelser!G66) -> 479.70841 | K23: =J23*(1+Antagelser!H66) -> 508.49091 | L23: =K23*(1+Antagelser!I66) -> 536.45791 | M23: =L23*(1+Antagelser!J66) -> 563.28081 | ... O23: =N23*(1+Antagelser!L66) -> 612.17358
B24: Vekst | D24: =(D23-C23)/C23 -> -0.027221527 | E24: =(E23-D23)/D23 -> 0.055001608 | F24: =(F23-E23)/E23 -> 0.075 | G24: =(G23-F23)/F23 -> 0.08 | H24: =(H23-G23)/G23 -> 0.08 | I24: =(I23-H23)/H23 -> 0.08 | J24: =(J23-I23)/I23 -> 0.08 | K24: =(K23-J23)/J23 -> 0.06 | ... O24: =(O23-N23)/N23 -> 0.04
B25: Bruttomargin | C25: 0.407 | D25: 0.429 | E25: 0.469 | F25: =Antagelser!C67 -> 0.44 | G25: =Antagelser!D67 -> 0.46 | H25: =Antagelser!E67 -> 0.46 | I25: =Antagelser!F67 -> 0.465 | J25: =Antagelser!G67 -> 0.465 | K25: =Antagelser!H67 -> 0.465 | L25: =Antagelser!I67 -> 0.465 | M25: =Antagelser!J67 -> 0.465 | ... O25: =Antagelser!L67 -> 0.465
B26: Bruttobidrag | C26: =C23*C25 -> 130.0772 | D26: =D23*D25 -> 133.3761 | E26: =E23*E25 -> 153.832 | F26: =F23*F25 -> 155.144 | G26: =G23*G25 -> 175.17168 | H26: =H23*H25 -> 189.18541 | I26: =I23*I25 -> 206.54112 | J26: =J23*J25 -> 223.06441 | ... O26: =O23*O25 -> 284.66072
B27: Driftskostnader | C27: 122.4 | D27: 112.6 | E27: 110.3 | F27: =E27*(1+Antagelser!C68) -> 114.712 | G27: =F27*(1+Antagelser!D68) -> 118.15336 | H27: =G27*(1+Antagelser!E68) -> 121.69796 | I27: =H27*(1+Antagelser!F68) -> 125.3489 | J27: =I27*(1+Antagelser!G68) -> 129.10937 | K27: =J27*(1+Antagelser!H68) -> 136.85593 | L27: =K27*(1+Antagelser!I68) -> 144.383 | M27: =L27*(1+Antagelser!J68) -> 151.60215 | ... O27: =N27*(1+Antagelser!L68) -> 164.76122
B28: Justert EBITA | C28: =C26-C27 -> 7.6772 | D28: =D26-D27 -> 20.7761 | E28: =E26-E27 -> 43.532 | F28: =F26-F27 -> 40.432 | G28: =G26-G27 -> 57.01832 | H28: =H26-H27 -> 67.487454 | I28: =I26-I27 -> 81.19222 | J28: =J26-J27 -> 93.955043 | ... O28: =O26-O27 -> 119.89949
B29: Justert EBITA-margin | C29: =C28/C23 -> 0.024021277 | D29: =D28/D23 -> 0.066825667 | E29: =E28/E23 -> 0.13271951 | F29: =F28/F23 -> 0.11466818 | G29: =G28/G23 -> 0.14972984 | H29: =H28/H23 -> 0.1640942 | I29: =I28/I23 -> 0.18279354 | J29: =J28/J23 -> 0.19585865 | ... O29: =O28/O23 -> 0.19585865
B31: HORIZON
B32: Omsetning | C32: 0.8 | D32: 7.4 | E32: 32.3 | F32: 48 | G32: =60*1.2 -> 72 | H32: =75*1.2 -> 90 | I32: =90*1.2 -> 108 | J32: =105*1.2 -> 126 | K32: ='Forecast Base'!K32*1.2 -> 141.6 | L32: ='Forecast Base'!L32*1.2 -> 156 | M32: ='Forecast Base'!M32*1.2 -> 169.2 | N32: ='Forecast Base'!N32*1.2 -> 181.2 | O32: ='Forecast Base'!O32*1.2 -> 192
B33: Vekst | D33: =(D32-C32)/C32 -> 8.25 | E33: =(E32-D32)/D32 -> 3.3648649 | F33: =(F32-E32)/E32 -> 0.48606811 | G33: =(G32-F32)/F32 -> 0.5 | H33: =(H32-G32)/G32 -> 0.25 | I33: =(I32-H32)/H32 -> 0.2 | J33: =(J32-I32)/I32 -> 0.16666667 | K33: =(K32-J32)/J32 -> 0.12380952 | ... O33: =(O32-N32)/N32 -> 0.059602649
B34: Bruttomargin | C34: -1.194 | D34: 0.501 | E34: 0.594 | F34: 0.6 | G34: 0.62 | H34: 0.64 | I34: 0.65 | J34: 0.655 | K34: 0.66 | L34: 0.665 | M34: 0.67 | N34: 0.67 | O34: 0.67
B35: Bruttobidrag | C35: =C34*C32 -> -0.9552 | D35: =D34*D32 -> 3.7074 | E35: =E34*E32 -> 19.1862 | F35: =F34*F32 -> 28.8 | G35: =G34*G32 -> 44.64 | H35: =H34*H32 -> 57.6 | I35: =I34*I32 -> 70.2 | J35: =J34*J32 -> 82.53 | ... O35: =O34*O32 -> 128.64
B36: Driftskostnader | C36: 7.2 | D36: 11.1 | E36: 23.9 | F36: 29 | G36: =34*1.1 -> 37.4 | H36: =40*1.1 -> 44 | I36: =48*1.1 -> 52.8 | J36: =52*1.1 -> 57.2 | K36: ='Forecast Base'!K36*1.1 -> 64.9 | L36: ='Forecast Base'!L36*1.1 -> 71.5 | M36: ='Forecast Base'!M36*1.1 -> 78.1 | N36: ='Forecast Base'!N36*1.1 -> 84.7 | O36: ='Forecast Base'!O36*1.1 -> 90.2
B37: EBITA | C37: =C35-C36 -> -8.1552 | D37: =D35-D36 -> -7.3926 | E37: =E35-E36 -> -4.7138 | F37: =F35-F36 -> -0.2 | G37: =G35-G36 -> 7.24 | H37: =H35-H36 -> 13.6 | I37: =I35-I36 -> 17.4 | J37: =J35-J36 -> 25.33 | ... O37: =O35-O36 -> 38.44
B38: EBITA-margin | C38: =C37/C32 -> -10.194 | D38: =D37/D32 -> -0.999 | E38: =E37/E32 -> -0.14593808 | F38: =F37/F32 -> -0.0041666667 | G38: =G37/G32 -> 0.10055556 | H38: =H37/H32 -> 0.15111111 | I38: =I37/I32 -> 0.16111111 | J38: =J37/J32 -> 0.20103175 | ... O38: =O37/O32 -> 0.20020833
B40: KONSERNFUNKSJONER | C40: -14.7 | D40: -22.7 | E40: -17 | F40: =(C40+D40+E40)/3 -> -18.133333 | G40: -18.7 | H40: -19.3 | I40: -19.9 | J40: -20.5 | K40: ='Forecast Base'!K40 -> -21.5 | L40: ='Forecast Base'!L40 -> -22.5 | M40: ='Forecast Base'!M40 -> -23.5 | N40: ='Forecast Base'!N40 -> -24.5 | O40: ='Forecast Base'!O40 -> -25.5
B41: EBITA | C41: =C10+C19+C28+C37+C40 -> 161.6768 | D41: =D10+D19+D28+D37+D40 -> 181.5071 | E41: =E10+E19+E28+E37+E40 -> 171.6881 | F41: =F10+F19+F28+F37+F40 -> 213.03254 | G41: =G10+G19+G28+G37+G40 -> 281.96724 | H41: =H10+H19+H28+H37+H40 -> 341.56437 | I41: =I10+I19+I28+I37+I40 -> 403.54553 | J41: =J10+J19+J28+J37+J40 -> 463.95789 | ... O41: =O10+O19+O28+O37+O40 -> 609.54822
B43: TOMRA GROUP
B44: Omsetning | C44: =C32+C23+C14+C5 -> 1287.9 | D44: =D32+D23+D14+D5 -> 1357.2 | E44: =E32+E23+E14+E5 -> 1319 | F44: =F32+F23+F14+F5 -> 1493.449 | G44: =G32+G23+G14+G5 -> 1646.13 | H44: =H32+H23+H14+H5 -> 1808.9781 | I44: =I32+I23+I14+I5 -> 1974.9463 | J44: =J32+J23+J14+J5 -> 2143.7362 | ... O44: =O32+O23+O14+O5 -> 2812.1427
B45: Vekst | D45: =(D44-C44)/C44 -> 0.053808526 | E45: =(E44-D44)/D44 -> -0.028146183 | F45: =(F44-E44)/E44 -> 0.13225853 | G45: =(G44-F44)/F44 -> 0.10223379 | H45: =(H44-G44)/G44 -> 0.098927911 | I45: =(I44-H44)/H44 -> 0.091746904 | J45: =(J44-I44)/I44 -> 0.08546555 | K45: =(K44-J44)/J44 -> 0.067337721 | ... O45: =(O44-N44)/N44 -> 0.044167133
B46: Bruttobidrag | C46: =C35+C26+C17+C8 -> 548.3768 | D46: =D35+D26+D17+D8 -> 590.5071 | E46: =E35+E26+E17+E8 -> 585.8881 | F46: =F35+F26+F17+F8 -> 646.82787 | G46: =G35+G26+G17+G8 -> 734.82994 | H46: =H35+H26+H17+H8 -> 815.55897 | I46: =I35+I26+I17+I8 -> 902.15093 | J46: =J35+J26+J17+J8 -> 983.34602 | ... O46: =O35+O26+O17+O8 -> 1297.9641
B47: Bruttomargin | C47: =C46/C44 -> 0.42579144 | D47: =D46/D44 -> 0.43509218 | E47: =E46/E44 -> 0.44419113 | F47: =F46/F44 -> 0.43311012 | G47: =G46/G44 -> 0.4463985 | H47: =H46/H44 -> 0.45083959 | I47: =I46/I44 -> 0.45679771 | J47: =J46/J44 -> 0.45870664 | ... O47: =O46/O44 -> 0.461557
B48: Justert EBITA | C48: =C41 -> 161.6768 | D48: =D41 -> 181.5071 | E48: =E41 -> 171.6881 | F48: =F41 -> 213.03254 | G48: =G41 -> 281.96724 | H48: =H41 -> 341.56437 | I48: =I41 -> 403.54553 | J48: =J41 -> 463.95789 | ... O48: =O41 -> 609.54822
B49: Justert EBITA-margin | C49: =C48/C44 -> 0.12553521 | D49: =D48/D44 -> 0.13373644 | E49: =E48/E44 -> 0.13016535 | F49: =F48/F44 -> 0.14264467 | G49: =G48/G44 -> 0.171291 | H49: =H48/H44 -> 0.1888162 | I49: =I48/I44 -> 0.20433241 | J49: =J48/J44 -> 0.2164249 | ... O49: =O48/O44 -> 0.2167558
B51: EUR mill | C51: =F4 -> 2026E | D51: =G4 -> 2027E | E51: =H4 -> 2028E | F51: =I4 -> 2029E | G51: =J4 -> 2030E | H51: =K4 -> 2031E | I51: =L4 -> 2032E | J51: =M4 -> 2033E | ... L51: =O4 -> 2035E
B52: Omsetning | C52: =F44 -> 1493.449 | D52: =G44 -> 1646.13 | E52: =H44 -> 1808.9781 | F52: =I44 -> 1974.9463 | G52: =J44 -> 2143.7362 | H52: =K44 -> 2288.0905 | I52: =L44 -> 2428.7374 | J52: =M44 -> 2564.2557 | ... L52: =O44 -> 2812.1427
B53: Justert EBITA | C53: =F48 -> 213.03254 | D53: =G48 -> 281.96724 | E53: =H48 -> 341.56437 | F53: =I48 -> 403.54553 | G53: =J48 -> 463.95789 | H53: =K48 -> 495.55743 | I53: =L48 -> 527.05355 | J53: =M48 -> 557.00445 | ... L53: =O48 -> 609.54822
B54: EBITA-margin | C54: =F49 -> 0.14264467 | D54: =G49 -> 0.171291 | E54: =H49 -> 0.1888162 | F54: =I49 -> 0.20433241 | G54: =J49 -> 0.2164249 | H54: =K49 -> 0.21658122 | I54: =L49 -> 0.21700722 | J54: =M49 -> 0.21721876 | ... L54: =O49 -> 0.2167558
B55: Amortisering av immatrielle eiendeler | C55: =C52*Antagelser!C71 -> 29.86898 | D55: =D52*Antagelser!D71 -> 31.276469 | E55: =E52*Antagelser!E71 -> 32.561607 | F55: =F52*Antagelser!F71 -> 33.574087 | G55: =G52*Antagelser!G71 -> 36.443515 | H55: =H52*Antagelser!H71 -> 36.609448 | I55: =I52*Antagelser!I71 -> 36.431062 | J55: =J52*Antagelser!J71 -> 35.89958 | ... L55: =L52*Antagelser!L71 -> 33.745712
B56: Justert EBIT | C56: =C53-C55 -> 183.16356 | D56: =D53-D55 -> 250.69077 | E56: =E53-E55 -> 309.00277 | F56: =F53-F55 -> 369.97144 | G56: =G53-G55 -> 427.51437 | H56: =H53-H55 -> 458.94798 | I56: =I53-I55 -> 490.62249 | J56: =J53-J55 -> 521.10487 | ... L56: =L53-L55 -> 575.80251
B57: Skattesats | C57: =Antagelser!C72 -> 0.24 | D57: =Antagelser!D72 -> 0.24 | E57: =Antagelser!E72 -> 0.24 | F57: =Antagelser!F72 -> 0.24 | G57: =Antagelser!G72 -> 0.24 | H57: =Antagelser!H72 -> 0.24 | I57: =Antagelser!I72 -> 0.24 | J57: =Antagelser!J72 -> 0.24 | ... L57: =Antagelser!L72 -> 0.24
B58: NOPAT | C58: =C56*(1-C57) -> 139.2043 | D58: =D56*(1-D57) -> 190.52498 | E58: =E56*(1-E57) -> 234.8421 | F58: =F56*(1-F57) -> 281.1783 | G58: =G56*(1-G57) -> 324.91092 | H58: =H56*(1-H57) -> 348.80046 | I58: =I56*(1-I57) -> 372.87309 | J58: =J56*(1-J57) -> 396.0397 | ... L58: =L56*(1-L57) -> 437.60991
B59: Avskrivninger og amortisering | C59: =C52*Antagelser!C73 -> 126.94316 | D59: =D52*Antagelser!D73 -> 136.62879 | E59: =E52*Antagelser!E73 -> 144.71825 | F59: =F52*Antagelser!F73 -> 154.04581 | G59: =G52*Antagelser!G73 -> 160.78021 | H59: =H52*Antagelser!H73 -> 167.0306 | I59: =I52*Antagelser!I73 -> 172.44036 | J59: =J52*Antagelser!J73 -> 176.93364 | ... L59: =L52*Antagelser!L73 -> 182.78927
B60: Capex | C60: =C52*Antagelser!C74 -> 141.87765 | D60: =D52*Antagelser!D74 -> 139.92105 | E60: =E52*Antagelser!E74 -> 144.71825 | F60: =F52*Antagelser!F74 -> 148.12097 | G60: =G52*Antagelser!G74 -> 150.06153 | H60: =H52*Antagelser!H74 -> 160.16633 | I60: =I52*Antagelser!I74 -> 170.01162 | J60: =J52*Antagelser!J74 -> 176.93364 | ... L60: =L52*Antagelser!L74 -> 191.2257
B61: Arbeidskapital | C61: =C52*Antagelser!C75 -> 358.42776 | D61: =D52*Antagelser!D75 -> 370.37924 | E61: =E52*Antagelser!E75 -> 379.88541 | F61: =F52*Antagelser!F75 -> 404.86399 | G61: =G52*Antagelser!G75 -> 428.74723 | H61: =H52*Antagelser!H75 -> 457.61809 | I61: =I52*Antagelser!I75 -> 480.89001 | J61: =J52*Antagelser!J75 -> 505.15838 | ... L61: =L52*Antagelser!L75 -> 548.36782
B62: Endring i arbeidskapital | C62: =C61-'Historiske finansielle tall'!J35 -> 29.72776 | D62: =D61-C61 -> 11.951479 | E62: =E61-D61 -> 9.5061722 | F62: =F61-E61 -> 24.978579 | G62: =G61-F61 -> 23.883243 | H62: =H61-G61 -> 28.870862 | I62: =I61-H61 -> 23.27192 | J62: =J61-I61 -> 24.268362 | K62: =K61-J61 -> 22.707275 | L62: =L61-K61 -> 20.50217
B63: FCFF | C63: =C58+C59-C60-C62 -> 94.542053 | D63: =D58+D59-D60-D62 -> 175.28125 | E63: =E58+E59-E60-E62 -> 225.33593 | F63: =F58+F59-F60-F62 -> 262.12456 | G63: =G58+G59-G60-G62 -> 311.74636 | H63: =H58+H59-H60-H62 -> 326.79387 | I63: =I58+I59-I60-I62 -> 352.02991 | J63: =J58+J59-J60-J62 -> 371.77134 | ... L63: =L58+L59-L60-L62 -> 408.67131
B64: FCFF-margin | C64: =C63/C52 -> 0.063304507 | D64: =D63/D52 -> 0.10648081 | E64: =E63/E52 -> 0.12456531 | F64: =F63/F52 -> 0.1327249 | G64: =G63/G52 -> 0.14542198 | H64: =H63/H52 -> 0.14282384 | I64: =I63/I52 -> 0.14494358 | J64: =J63/J52 -> 0.14498216 | ... L64: =L63/L52 -> 0.14532382

Sheet DCF
B2: TOMRA ASA - DCF
B4: DCF
B5: Antall aksjer | C5: ='Historiske finansielle tall'!C5 -> 296040156
B6: EUR/NOK | C6: 10.92
B9: DCF Base
M10: Terminal
B11: EUR mill | C11: 2026E | D11: 2027E | E11: 2028E | F11: 2029E | G11: 2030E | H11: 2031E | I11: 2032E | J11: 2033E | K11: 2034E | L11: 2035E | M11: 2036E
B12: FCFF | C12: ='Forecast Base'!C63 -> 59.581253 | D12: ='Forecast Base'!D63 -> 116.88699 | E12: ='Forecast Base'!E63 -> 148.4165 | F12: ='Forecast Base'!F63 -> 179.7021 | G12: ='Forecast Base'!G63 -> 208.2105 | H12: ='Forecast Base'!H63 -> 218.89802 | I12: ='Forecast Base'!I63 -> 236.68222 | J12: ='Forecast Base'!J63 -> 248.37163 | ... L12: ='Forecast Base'!L63 -> 258.44688 | M12: =L12*(1+C14) -> 263.61582
B13: Periode | C13: 1 | D13: 2 | E13: 3 | F13: 4 | G13: 5 | H13: 6 | I13: 7 | J13: 8 | K13: 9 | L13: 10
B14: Terminalvekst | C14: 0.02
B15: WACC | C15: =WACC!C32 -> 0.08323486
B16: Diskonteringsfaktor | C16: =1/(1+$C$15)^C13 -> 0.92316084 | D16: =1/(1+$C$15)^D13 -> 0.85222593 | E16: =1/(1+$C$15)^E13 -> 0.7867416 | F16: =1/(1+$C$15)^F13 -> 0.72628904 | G16: =1/(1+$C$15)^G13 -> 0.6704816 | H16: =1/(1+$C$15)^H13 -> 0.61896235 | I16: =1/(1+$C$15)^I13 -> 0.5714018 | J16: =1/(1+$C$15)^J13 -> 0.52749577 | ... L16: =1/(1+$C$15)^L13 -> 0.44954557
B17: Nåverdi FCFF | C17: =C12*C16 -> 55.003079 | D17: =D12*D16 -> 99.614128 | E17: =E12*E16 -> 116.76544 | F17: =F12*F16 -> 130.51567 | G17: =G12*G16 -> 139.60131 | H17: =H12*H16 -> 135.48963 | I17: =I12*I16 -> 135.24065 | J17: =J12*J16 -> 131.01498 | ... L17: =L12*L16 -> 116.18365
B18: Terminalverdi | L18: =M12/(C15-C14) -> 4168.837
B19: Terminal nv | L19: =L18*L16 -> 1874.0822
B20: Enterprise value | C20: =C17+D17+E17+F17+G17+H17+I17+J17+L17+K17+L19 -> 3057.465
B21: Netto rentebærende gjeld | C21: =505+55-69 -> 491
B22: Leasinggjeld | C22: =105+44 -> 149
B23: Minoritetsinteresser | C23: 40
B24: Andre justeringer | C24: 0
B25: Egenkapitalverdi | C25: =C20-C21-C22-C23-C24 -> 2377.465
B27: Verdi per aksje | C27: =C25/(C5/1000000) -> 8.0308868
B28: Verdi per aksje i NOK | C28: =C27*C6 -> 87.697284
B33: DCF Bear
M34: Terminal
B35: EUR mill | C35: 2026E | D35: 2027E | E35: 2028E | F35: 2029E | G35: 2030E | H35: 2031E | I35: 2032E | J35: 2033E | K35: 2034E | L35: 2035E | M35: 2036E
B36: FCFF | C36: ='Forecast Bear'!C63 -> 30.923465 | D36: ='Forecast Bear'!D63 -> 80.663167 | E36: ='Forecast Bear'!E63 -> 96.361654 | F36: ='Forecast Bear'!F63 -> 116.62594 | G36: ='Forecast Bear'!G63 -> 132.33098 | H36: ='Forecast Bear'!H63 -> 127.2681 | I36: ='Forecast Bear'!I63 -> 144.05243 | J36: ='Forecast Bear'!J63 -> 157.05318 | ... L36: ='Forecast Bear'!L63 -> 171.20359 | M36: =L36*(1+C38) -> 174.62766
B37: Periode | C37: 1 | D37: 2 | E37: 3 | F37: 4 | G37: 5 | H37: 6 | I37: 7 | J37: 8 | K37: 9 | L37: 10
B38: Terminalvekst | C38: 0.02
B39: WACC | C39: =C15 -> 0.08323486
B40: Diskonteringsfaktor | C40: =1/(1+$C$39)^C37 -> 0.92316084 | D40: =1/(1+$C$39)^D37 -> 0.85222593 | E40: =1/(1+$C$39)^E37 -> 0.7867416 | F40: =1/(1+$C$39)^F37 -> 0.72628904 | G40: =1/(1+$C$39)^G37 -> 0.6704816 | H40: =1/(1+$C$39)^H37 -> 0.61896235 | I40: =1/(1+$C$39)^I37 -> 0.5714018 | J40: =1/(1+$C$39)^J37 -> 0.52749577 | ... L40: =1/(1+$C$39)^L37 -> 0.44954557
B41: Nåverdi FCFF | C41: =C36*C40 -> 28.547332 | D41: =D36*D40 -> 68.743242 | E41: =E36*E40 -> 75.811723 | F41: =F36*F40 -> 84.704145 | G41: =G36*G40 -> 88.725484 | H41: =H36*H40 -> 78.774164 | I41: =I36*I40 -> 82.311817 | J41: =J36*J40 -> 82.844889 | ... L41: =L36*L40 -> 76.963816
B42: Terminalverdi | L42: =M36/(C39-C38) -> 2761.5727
B43: Terminal nv | L43: =L42*L40 -> 1241.4528
B44: Enterprise value | C44: =C41+D41+E41+F41+G41+H41+I41+J41+K41+L41+L43 -> 1988.1083
B45: Netto rentebærende gjeld | C45: =505+55-69 -> 491
B46: Leasinggjeld | C46: =105+44 -> 149
B47: Minoritetsinteresser | C47: 40
B48: Andre justeringer | C48: 0
B49: Egenkapitalverdi | C49: =C44-C45-C46-C47-C48 -> 1308.1083
B51: Verdi per aksje | C51: =C49/(C5/1000000) -> 4.4186853
B52: Verdi per aksje i NOK | C52: =C51*C6 -> 48.252043
B57: DCF Bull
M58: Terminal
B59: EUR mill | C59: 2026E | D59: 2027E | E59: 2028E | F59: 2029E | G59: 2030E | H59: 2031E | I59: 2032E | J59: 2033E | K59: 2034E | L59: 2035E | M59: 2036E
B60: FCFF | C60: ='Forecast Bull'!C63 -> 94.542053 | D60: ='Forecast Bull'!D63 -> 175.28125 | E60: ='Forecast Bull'!E63 -> 225.33593 | F60: ='Forecast Bull'!F63 -> 262.12456 | G60: ='Forecast Bull'!G63 -> 311.74636 | H60: ='Forecast Bull'!H63 -> 326.79387 | I60: ='Forecast Bull'!I63 -> 352.02991 | J60: ='Forecast Bull'!J63 -> 371.77134 | ... L60: ='Forecast Bull'!L63 -> 408.67131 | M60: =L60*(1+C62) -> 416.84474
B61: Periode | C61: 1 | D61: 2 | E61: 3 | F61: 4 | G61: 5 | H61: 6 | I61: 7 | J61: 8 | K61: 9 | L61: 10
B62: Terminalvekst | C62: 0.02
B63: WACC | C63: =C39 -> 0.08323486
B64: Diskonteringsfaktor | C64: =1/(1+$C$63)^C61 -> 0.92316084 | D64: =1/(1+$C$63)^D61 -> 0.85222593 | E64: =1/(1+$C$63)^E61 -> 0.7867416 | F64: =1/(1+$C$63)^F61 -> 0.72628904 | G64: =1/(1+$C$63)^G61 -> 0.6704816 | H64: =1/(1+$C$63)^H61 -> 0.61896235 | I64: =1/(1+$C$63)^I61 -> 0.5714018 | J64: =1/(1+$C$63)^J61 -> 0.52749577 | ... L64: =1/(1+$C$63)^L61 -> 0.44954557
B65: Nåverdi FCFF | C65: =C60*C64 -> 87.277521 | D65: =D60*D64 -> 149.37922 | E65: =E60*E64 -> 177.28115 | F65: =F60*F64 -> 190.37819 | G65: =G60*G64 -> 209.0202 | H65: =H60*H64 -> 202.2731 | I65: =I60*I64 -> 201.15052 | J65: =J60*J64 -> 196.10781 | ... L65: =L60*L64 -> 183.71638
B66: Terminalverdi | L66: =M60/(C63-C62) -> 6592.0085
B67: Terminal nv | L67: =L66*L64 -> 2963.4082
B68: Enterprise value | C68: =C65+D65+E65+F65+G65+H65+I65+J65+K65+L65+L67 -> 4750.8569
B69: Netto rentebærende gjeld | C69: =505+55-69 -> 491
B70: Leasinggjjeld | C70: =105+44 -> 149
B71: Minoritetsinteresser | C71: 40
B72: Andre justeringer | C72: 0
B73: Egenkapitalverdi | C73: =C68-C69-C70-C71-C72 -> 4070.8569
B75: Verdi per aksje | C75: =C73/(C5/1000000) -> 13.75103
B76: Verdi per aksje i NOK | C76: =C75*C6 -> 150.16124
B79: Sannsynlighetsvekter resultatene:
B81: Base sannsynlighet | C81: 0.6
B82: Bear sannsynlighet | C82: 0.25
B83: Bull sannsynlighet | C83: 0.15
B85: Verdi per aksje (vektet snitt) | C85: =(C81*C28)+(C82*C52)+(C83*C76) -> 87.205567
B87: Sensitivitetsanalyse
C88: WACC
B89: =$C$28 -> 87.697284 | C89: 0.0732 | D89: 0.0782 | E89: 0.0832 | F89: 0.0882 | G89: 0.0932
B90: 0.01 | C90: 96.189367 | D90: 86.270069 | E90: 77.728109 | F90: 70.298634 | G90: 63.780484
B91: 0.015 | C91: 103.05131 | D91: 91.88595 | E91: 82.379041 | F91: 74.190134 | G91: 67.065872
B92: 0.02 | C92: 111.2031 | D92: 98.466759 | E92: 87.76588 | F92: 78.652234 | G92: 70.800083
B93: 0.025 | C93: 121.04612 | D93: 106.28456 | E93: 94.078292 | F93: 83.820364 | G93: 75.081833
B94: 0.03 | C94: 133.16763 | D94: 115.72432 | E94: 101.57725 | F94: 89.876488 | G94: 80.041074
B98: DCF-resultat | C98: Bear | D98: Base | E98: Bull
B99: Verdi per aksje | C99: =C52 -> 48.252043 | D99: =C28 -> 87.697284 | E99: =C76 -> 150.16124
B100: Oppside/nedside | C100: =(C99-'Historiske finansielle tall'!C4)/'Historiske finansielle tall'!C4 -> -0.53957974 | D100: =(D99-'Historiske finansielle tall'!C4)/'Historiske finansielle tall'!C4 -> -0.16319386 | E100: =(E99-'Historiske finansielle tall'!C4)/'Historiske finansielle tall'!C4 -> 0.43283628

Sheet Reverse DCF
B2: TOMRA ASA - Reverse DCF
B4: Dagens aksjekurs | C4: ='Historiske finansielle tall'!C4 -> 104.8
B5: Base DCF-verdi | C5: =DCF!C28 -> 87.697284
B6: WACC | C6: =WACC!C32 -> 0.08323486
B7: Terminalvekst | C7: 0.02
B8: Forskjell mot markedskurs | C8: =C4-C5 -> 17.102716
B10: Marginpåslag 2035, pp | C10: 0.024712185
B12: Reverse DCF basert på EBITA-margin
C13: ='Forecast Base'!E4 -> 2025 | D13: ='Forecast Base'!F4 -> 2026E | E13: ='Forecast Base'!G4 -> 2027E | F13: ='Forecast Base'!H4 -> 2028E | G13: ='Forecast Base'!I4 -> 2029E | H13: ='Forecast Base'!J4 -> 2030E | I13: ='Forecast Base'!K4 -> 2031E | J13: ='Forecast Base'!L4 -> 2032E | ... M13: ='Forecast Base'!O4 -> 2035E
B14: Base EBITA-margin | C14: ='Forecast Base'!E49 -> 0.13016535 | D14: ='Forecast Base'!F49 -> 0.13015619 | E14: ='Forecast Base'!G49 -> 0.1502628 | F14: ='Forecast Base'!H49 -> 0.16236099 | G14: ='Forecast Base'!I49 -> 0.16882573 | H14: ='Forecast Base'!J49 -> 0.17587806 | I14: ='Forecast Base'!K49 -> 0.17789446 | J14: ='Forecast Base'!L49 -> 0.17920995 | ... M14: ='Forecast Base'!O49 -> 0.17690804
B15: Innfasing | D15: 0.1 | E15: 0.2 | F15: 0.3 | G15: 0.4 | H15: 0.5 | I15: 0.6 | J15: 0.7 | K15: 0.8 | L15: 0.9 | M15: 1
B16: Implisitt EBITA-margin | C16: =C14+$C$10*C15 -> 0.13016535 | D16: =D14+$C$10*D15 -> 0.13262741 | E16: =E14+$C$10*E15 -> 0.15520524 | F16: =F14+$C$10*F15 -> 0.16977465 | G16: =G14+$C$10*G15 -> 0.1787106 | H16: =H14+$C$10*H15 -> 0.18823416 | I16: =I14+$C$10*I15 -> 0.19272177 | J16: =J14+$C$10*J15 -> 0.19650848 | ... M16: =M14+$C$10*M15 -> 0.20162023
C19: =D13 -> 2026E | D19: =E13 -> 2027E | E19: =F13 -> 2028E | F19: =G13 -> 2029E | G19: =H13 -> 2030E | H19: =I13 -> 2031E | I19: =J13 -> 2032E | J19: =K13 -> 2033E | ... L19: =M13 -> 2035E
B20: Base omsetning | C20: ='Forecast Base'!F44 -> 1480.04 | D20: ='Forecast Base'!G44 -> 1603.0936 | E20: ='Forecast Base'!H44 -> 1732.8263 | F20: ='Forecast Base'!I44 -> 1854.2302 | G20: ='Forecast Base'!J44 -> 1977.7436 | H20: ='Forecast Base'!K44 -> 2092.6105 | I20: ='Forecast Base'!L44 -> 2203.341 | J20: ='Forecast Base'!M44 -> 2307.6414 | ... L20: ='Forecast Base'!O44 -> 2486.0392
B21: Implisitt EBITA-margin | C21: =D16 -> 0.13262741 | D21: =E16 -> 0.15520524 | E21: =F16 -> 0.16977465 | F21: =G16 -> 0.1787106 | G21: =H16 -> 0.18823416 | H21: =I16 -> 0.19272177 | I21: =J16 -> 0.19650848 | J21: =K16 -> 0.19924681 | ... L21: =M16 -> 0.20162023
B22: Implisitt EBITA | C22: =C20*C21 -> 196.29387 | D22: =D20*D21 -> 248.80852 | E22: =E20*E21 -> 294.18998 | F22: =F20*F21 -> 331.3706 | G22: =G20*G21 -> 372.2789 | H22: =H20*H21 -> 403.29161 | I22: =I20*I21 -> 432.9752 | J22: =J20*J21 -> 459.79018 | ... L22: =L20*L21 -> 501.23578
B25: Implisitt EBITA | C25: =C22 -> 196.29387 | D25: =D22 -> 248.80852 | E25: =E22 -> 294.18998 | F25: =F22 -> 331.3706 | G25: =G22 -> 372.2789 | H25: =H22 -> 403.29161 | I25: =I22 -> 432.9752 | J25: =J22 -> 459.79018 | ... L25: =L22 -> 501.23578
B26: Amortisering | C26: ='Forecast Base'!C55 -> 29.6008 | D26: ='Forecast Base'!D55 -> 30.458778 | E26: ='Forecast Base'!E55 -> 31.190874 | F26: ='Forecast Base'!F55 -> 31.521914 | G26: ='Forecast Base'!G55 -> 33.621642 | H26: ='Forecast Base'!H55 -> 33.481768 | I26: ='Forecast Base'!I55 -> 33.050116 | J26: ='Forecast Base'!J55 -> 32.306979 | ... L26: ='Forecast Base'!L55 -> 29.83247
B27: Implisitt EBIT | C27: =C25-C26 -> 166.69307 | D27: =D25-D26 -> 218.34974 | E27: =E25-E26 -> 262.9991 | F27: =F25-F26 -> 299.84868 | G27: =G25-G26 -> 338.65726 | H27: =H25-H26 -> 369.80984 | I27: =I25-I26 -> 399.92509 | J27: =J25-J26 -> 427.4832 | ... L27: =L25-L26 -> 471.40331
B28: Skatt | C28: 0.245 | D28: 0.245 | E28: 0.245 | F28: 0.245 | G28: 0.245 | H28: 0.245 | I28: 0.245 | J28: 0.245 | K28: 0.245 | L28: 0.245
B29: Implisitt NOPAT | C29: =C27*(1-C28) -> 125.85327 | D29: =D27*(1-D28) -> 164.85406 | E29: =E27*(1-E28) -> 198.56432 | F29: =F27*(1-F28) -> 226.38576 | G29: =G27*(1-G28) -> 255.68623 | H29: =H27*(1-H28) -> 279.20643 | I29: =I27*(1-I28) -> 301.94344 | J29: =J27*(1-J28) -> 322.74982 | ... L29: =L27*(1-L28) -> 355.9095
B30: D&A | C30: ='Forecast Base'!C59 -> 125.8034 | D30: ='Forecast Base'!D59 -> 133.05677 | E30: ='Forecast Base'!E59 -> 138.62611 | F30: ='Forecast Base'!F59 -> 144.62996 | G30: ='Forecast Base'!G59 -> 148.33077 | H30: ='Forecast Base'!H59 -> 152.76057 | I30: ='Forecast Base'!I59 -> 156.43721 | J30: ='Forecast Base'!J59 -> 159.22726 | ... L30: ='Forecast Base'!L59 -> 161.59255
B31: Capex | C31: ='Forecast Base'!C60 -> 148.004 | D31: ='Forecast Base'!D60 -> 152.29389 | E31: ='Forecast Base'!E60 -> 155.95437 | F31: ='Forecast Base'!F60 -> 157.60957 | G31: ='Forecast Base'!G60 -> 158.21949 | H31: ='Forecast Base'!H60 -> 163.22362 | I31: ='Forecast Base'!I60 -> 171.8606 | J31: ='Forecast Base'!J60 -> 179.99603 | ... L31: ='Forecast Base'!L60 -> 193.91106
B32: Endring i arbeidskapital | C32: ='Forecast Base'!C62 -> 41.31 | D32: ='Forecast Base'!D62 -> 22.747932 | E32: ='Forecast Base'!E62 -> 23.120392 | F32: ='Forecast Base'!F62 -> 19.865776 | G32: ='Forecast Base'!G62 -> 19.136937 | H32: ='Forecast Base'!H62 -> 26.419382 | I32: ='Forecast Base'!I62 -> 21.061339 | J32: ='Forecast Base'!J62 -> 19.165196 | ... L32: ='Forecast Base'!L62 -> 18.760338
B33: Implisitt FCFF | C33: =C29+C30-C31-C32 -> 62.342667 | D33: =D29+D30-D31-D32 -> 122.869 | E33: =E29+E30-E31-E32 -> 158.11567 | F33: =F29+F30-F31-F32 -> 193.54037 | G33: =G29+G30-G31-G32 -> 226.66058 | H33: =H29+H30-H31-H32 -> 242.324 | I33: =I29+I30-I31-I32 -> 265.45871 | J33: =J29+J30-J31-J32 -> 282.81585 | ... L33: =L29+L30-L31-L32 -> 304.83065
B37: EUR mill | C37: 2026E | D37: 2027E | E37: 2028E | F37: 2029E | G37: 2030E | H37: 2031E | I37: 2032E | J37: 2033E | K37: 2034E | L37: 2035E | M37: 2036E
B38: Implisitt FCFF | C38: =C33 -> 62.342667 | D38: =D33 -> 122.869 | E38: =E33 -> 158.11567 | F38: =F33 -> 193.54037 | G38: =G33 -> 226.66058 | H38: =H33 -> 242.324 | I38: =I33 -> 265.45871 | J38: =J33 -> 282.81585 | ... L38: =L33 -> 304.83065 | M38: =L38*(1+C40) -> 310.92727
B39: Periode | C39: 1 | D39: 2 | E39: 3 | F39: 4 | G39: 5 | H39: 6 | I39: 7 | J39: 8 | K39: 9 | L39: 10
B40: Terminalvekst | C40: 0.02
B41: WACC | C41: =C6 -> 0.08323486
B42: Diskonteringsfaktor | C42: =1/(1+$C$41)^C39 -> 0.92316084 | D42: =1/(1+$C$41)^D39 -> 0.85222593 | E42: =1/(1+$C$41)^E39 -> 0.7867416 | F42: =1/(1+$C$41)^F39 -> 0.72628904 | G42: =1/(1+$C$41)^G39 -> 0.6704816 | H42: =1/(1+$C$41)^H39 -> 0.61896235 | I42: =1/(1+$C$41)^I39 -> 0.5714018 | J42: =1/(1+$C$41)^J39 -> 0.52749577 | ... L42: =1/(1+$C$41)^L39 -> 0.44954557
B43: Nåverdi FCFF | C43: =C38*C42 -> 57.552309 | D43: =D38*D42 -> 104.71215 | E43: =E38*E42 -> 124.39617 | F43: =F38*F42 -> 140.56625 | G43: =G38*G42 -> 151.97175 | H43: =H38*H42 -> 149.98943 | I43: =I38*I42 -> 151.68359 | J43: =J38*J42 -> 149.18416 | ... L43: =L38*L42 -> 137.03527
B44: Terminalverdi | L44: =M38/(C41-C40) -> 4917.0231
B45: Terminal nv | L45: =L44*L42 -> 2210.426
B46: Enterprise value | C46: =C43+D43+E43+F43+G43+H43+I43+J43+K43+L43+L45 -> 3521.118
B47: Netto rentebærende gjeld | C47: =505+55-69 -> 491
B48: Leasinggjjeld | C48: =105+44 -> 149
B49: Minoritetsinteresser | C49: 40
B50: Andre justeringer | C50: 0
B51: Egenkapitalverdi | C51: =C46-C47-C48-C49-C50 -> 2841.118
B53: Verdi per aksje | C53: =C51/(DCF!C5/1000000) -> 9.5970696
B54: Verdi per aksje i NOK | C54: =C53*DCF!C6 -> 104.8
B58: Reverse DCF basert på vekst
B60: Omsetningspåslag 2035 % | C60: 0.24544894
C62: =C19 -> 2026E | D62: =D19 -> 2027E | E62: =E19 -> 2028E | F62: =F19 -> 2029E | G62: =G19 -> 2030E | H62: =H19 -> 2031E | I62: =I19 -> 2032E | J62: =J19 -> 2033E | ... L62: =L19 -> 2035E
B63: Baseomsetning | C63: =C20 -> 1480.04 | D63: =D20 -> 1603.0936 | E63: =E20 -> 1732.8263 | F63: =F20 -> 1854.2302 | G63: =G20 -> 1977.7436 | H63: =H20 -> 2092.6105 | I63: =I20 -> 2203.341 | J63: =J20 -> 2307.6414 | ... L63: =L20 -> 2486.0392
B64: Base Omsetningsvekst | C64: ='Forecast Base'!F45 -> 0.12209249 | D64: ='Forecast Base'!G45 -> 0.083142077 | E64: ='Forecast Base'!H45 -> 0.080926496 | F64: ='Forecast Base'!I45 -> 0.070061182 | G64: ='Forecast Base'!J45 -> 0.0666117 | H64: ='Forecast Base'!K45 -> 0.058079762 | I64: ='Forecast Base'!L45 -> 0.052915019 | J64: ='Forecast Base'!M45 -> 0.047337359 | ... L64: ='Forecast Base'!O45 -> 0.034702905
B65: Innfasing | C65: 0.1 | D65: 0.2 | E65: 0.3 | F65: 0.4 | G65: 0.5 | H65: 0.6 | I65: 0.7 | J65: 0.8 | K65: 0.9 | L65: 1
B66: Implisitt omsetning | C66: =C63*(1+$C$60*C65) -> 1516.3674 | D66: =D63*(1+$C$60*D65) -> 1681.7891 | E66: =E63*(1+$C$60*E65) -> 1860.4225 | F66: =F63*(1+$C$60*F65) -> 2036.2777 | G66: =G63*(1+$C$60*G65) -> 2220.4612 | H66: =H63*(1+$C$60*H65) -> 2400.7879 | I66: =I63*(1+$C$60*I65) -> 2581.9064 | J66: =J63*(1+$C$60*J65) -> 2760.7679 | ... L66: =L63*(1+$C$60*L65) -> 3096.2349
B67: Implisit vekst | C67: =(C66-'Forecast Base'!E44)/'Forecast Base'!E44 -> 0.14963414 | D67: =(D66-C66)/C66 -> 0.10909078 | E67: =(E66-D66)/D66 -> 0.10621625 | F67: =(F66-E66)/E66 -> 0.09452438 | G67: =(G66-F66)/F66 -> 0.090451035 | H67: =(H66-G66)/G66 -> 0.0812114 | I67: =(I66-H66)/H66 -> 0.075441279 | J67: =(J66-I66)/I66 -> 0.069274953 | K67: =(K66-J66)/J66 -> 0.062536697 | L67: =(L66-K66)/K66 -> 0.055504436
C70: =C62 -> 2026E | D70: =D62 -> 2027E | E70: =E62 -> 2028E | F70: =F62 -> 2029E | G70: =G62 -> 2030E | H70: 2031E | I70: 2032E | J70: 2033E | K70: 2034E | L70: 2035E
B71: Implisitt omsetning | C71: =C66 -> 1516.3674 | D71: =D66 -> 1681.7891 | E71: =E66 -> 1860.4225 | F71: =F66 -> 2036.2777 | G71: =G66 -> 2220.4612 | H71: =H66 -> 2400.7879 | I71: =I66 -> 2581.9064 | J71: =J66 -> 2760.7679 | ... L71: =L66 -> 3096.2349
B72: Base EBITA-margin | C72: =D14 -> 0.13015619 | D72: =E14 -> 0.1502628 | E72: =F14 -> 0.16236099 | F72: =G14 -> 0.16882573 | G72: =H14 -> 0.17587806 | H72: =I14 -> 0.17789446 | I72: =J14 -> 0.17920995 | J72: =K14 -> 0.17947706 | ... L72: =M14 -> 0.17690804
B73: Implisitt EBITA | C73: =C71*C72 -> 197.36461 | D73: =D71*D72 -> 252.71034 | E73: =E71*E72 -> 302.06003 | F73: =F71*F72 -> 343.77607 | G73: =G71*G72 -> 390.53041 | H73: =H71*H72 -> 427.08688 | I73: =I71*I72 -> 462.70333 | J73: =J71*J72 -> 495.49451 | ... L73: =L71*L72 -> 547.74885
B74: Amortisering | C74: =C71*Antagelser!C19 -> 30.327348 | D74: =D71*Antagelser!D19 -> 31.953993 | E74: =E71*Antagelser!E19 -> 33.487604 | F74: =F71*Antagelser!F19 -> 34.616722 | G74: =G71*Antagelser!G19 -> 37.74784 | H74: =H71*Antagelser!H19 -> 38.412607 | I74: =I71*Antagelser!I19 -> 38.728597 | J74: =J71*Antagelser!J19 -> 38.650751 | ... L74: =L71*Antagelser!L19 -> 37.154818
B75: Implisitt EBIT | C75: =C73-C74 -> 167.03726 | D75: =D73-D74 -> 220.75635 | E75: =E73-E74 -> 268.57243 | F75: =F73-F74 -> 309.15935 | G75: =G73-G74 -> 352.78257 | H75: =H73-H74 -> 388.67428 | I75: =I73-I74 -> 423.97473 | J75: =J73-J74 -> 456.84376 | ... L75: =L73-L74 -> 510.59403
B76: Skattesats | C76: =C28 -> 0.245 | D76: =D28 -> 0.245 | E76: =E28 -> 0.245 | F76: =F28 -> 0.245 | G76: =G28 -> 0.245 | H76: =H28 -> 0.245 | I76: =I28 -> 0.245 | J76: =J28 -> 0.245 | ... L76: =L28 -> 0.245
B77: Implisitt NOPAT | C77: =C75*(1-C76) -> 126.11313 | D77: =D75*(1-D76) -> 166.67104 | E77: =E75*(1-E76) -> 202.77218 | F77: =F75*(1-F76) -> 233.41531 | G77: =G75*(1-G76) -> 266.35084 | H77: =H75*(1-H76) -> 293.44908 | I77: =I75*(1-I76) -> 320.10092 | J77: =J75*(1-J76) -> 344.91704 | ... L77: =L75*(1-L76) -> 385.49849
B78: D&A | C78: =C71*Antagelser!C21 -> 128.89123 | D78: =D71*Antagelser!D21 -> 139.5885 | E78: =E71*Antagelser!E21 -> 148.8338 | F78: =F71*Antagelser!F21 -> 158.82966 | G78: =G71*Antagelser!G21 -> 166.53459 | H78: =H71*Antagelser!H21 -> 175.25752 | I78: =I71*Antagelser!I21 -> 183.31536 | J78: =J71*Antagelser!J21 -> 190.49298 | ... L78: =L71*Antagelser!L21 -> 201.25527
B79: Capex | C79: =C71*Antagelser!C22 -> 151.63674 | D79: =D71*Antagelser!D22 -> 159.76997 | E79: =E71*Antagelser!E22 -> 167.43802 | F79: =F71*Antagelser!F22 -> 173.08361 | G79: =G71*Antagelser!G22 -> 177.63689 | H79: =H71*Antagelser!H22 -> 187.26146 | I79: =I71*Antagelser!I22 -> 201.3887 | J79: =J71*Antagelser!J22 -> 215.3399 | ... L79: =L71*Antagelser!L22 -> 241.50632
B80: Arbeidskapital | C80: =C71*Antagelser!C23 -> 379.09186 | D80: =D71*Antagelser!D23 -> 412.03834 | E80: =E71*Antagelser!E23 -> 446.50139 | F80: =F71*Antagelser!F23 -> 478.52527 | G80: =G71*Antagelser!G23 -> 510.70607 | H80: =H71*Antagelser!H23 -> 552.18123 | I80: =I71*Antagelser!I23 -> 588.67467 | J80: =J71*Antagelser!J23 -> 623.93354 | ... L80: =L71*Antagelser!L23 -> 696.65284
B81: Endring i arbeidskapital | C81: =C80-'Historiske finansielle tall'!J35 -> 50.391856 | D81: =D80-C80 -> 32.946479 | E81: =E80-D80 -> 34.463056 | F81: =F80-E80 -> 32.023879 | G81: =G80-F80 -> 32.1808 | H81: =H80-G80 -> 41.475155 | I81: =I80-H80 -> 36.493445 | J81: =J80-I80 -> 35.258874 | K81: =K80-J80 -> 36.085326 | L81: =L80-K80 -> 36.633975
B82: Implisitt FCFF | C82: =C77+C78-C79-C81 -> 52.975762 | D82: =D77+D78-D79-D81 -> 113.5431 | E82: =E77+E78-E79-E81 -> 149.7049 | F82: =F77+F78-F79-F81 -> 187.13749 | G82: =G77+G78-G79-G81 -> 223.06773 | H82: =H77+H78-H79-H81 -> 239.96998 | I82: =I77+I78-I79-I81 -> 265.53413 | J82: =J77+J78-J79-J81 -> 284.81125 | ... L82: =L77+L78-L79-L81 -> 308.61346
B85: EUR mill | C85: 2026E | D85: 2027E | E85: 2028E | F85: 2029E | G85: 2030E | H85: 2031E | I85: 2032E | J85: 2033E | K85: 2034E | L85: 2035E | M85: 2036E
B86: Implisitt FCFF | C86: =C82 -> 52.975762 | D86: =D82 -> 113.5431 | E86: =E82 -> 149.7049 | F86: =F82 -> 187.13749 | G86: =G82 -> 223.06773 | H86: =H82 -> 239.96998 | I86: =I82 -> 265.53413 | J86: =J82 -> 284.81125 | ... L86: =L82 -> 308.61346 | M86: =L86*(1+C88) -> 314.78573
B87: Periode | C87: 1 | D87: 2 | E87: 3 | F87: 4 | G87: 5 | H87: 6 | I87: 7 | J87: 8 | K87: 9 | L87: 10
B88: Terminalvekst | C88: 0.02
B89: WACC | C89: =C41 -> 0.08323486
B90: Diskonteringsfaktor | C90: =1/(1+$C$89)^C87 -> 0.92316084 | D90: =1/(1+$C$89)^D87 -> 0.85222593 | E90: =1/(1+$C$89)^E87 -> 0.7867416 | F90: =1/(1+$C$89)^F87 -> 0.72628904 | G90: =1/(1+$C$89)^G87 -> 0.6704816 | H90: =1/(1+$C$89)^H87 -> 0.61896235 | I90: =1/(1+$C$89)^I87 -> 0.5714018 | J90: =1/(1+$C$89)^J87 -> 0.52749577 | ... L90: =1/(1+$C$89)^L87 -> 0.44954557
B91: Nåverdi FCFF | C91: =C86*C90 -> 48.905149 | D91: =D86*D90 -> 96.764371 | E91: =E86*E90 -> 117.77908 | F91: =F86*F90 -> 135.91591 | G91: =G86*G90 -> 149.56281 | H91: =H86*H90 -> 148.53239 | I91: =I86*I90 -> 151.72668 | J91: =J86*J90 -> 150.23673 | ... L91: =L86*L90 -> 138.73582
B92: Terminalverdi | L92: =M86/(C89-C88) -> 4978.0411
B93: Terminal nv | L93: =L92*L90 -> 2237.8563
B94: Enterprise value | C94: =C91+D91+E91+F91+G91+H91+I91+J91+K91+L91+L93 -> 3521.118
B95: Netto rentebærende gjeld | C95: =505+55-69 -> 491
B96: Leasinggjjeld | C96: =105+44 -> 149
B97: Minoritetsinteresser | C97: 40
B98: Andre justeringer | C98: 0
B99: Egenkapitalverdi | C99: =C94-C95-C96-C97-C98 -> 2841.118
B101: Verdi per aksje | C101: =C99/(DCF!C5/1000000) -> 9.5970696
B102: Verdi per aksje i NOK | C102: =C101*DCF!C6 -> 104.8
B104: Implisitt OMS CAGR | C104: =(L71/'Forecast Base'!E44)^(1/10)-1 -> 0.089077812
B107: Nøkkelforutsetninger | C107: Base case | D107: Implisitt ved markedskurs | E107: Avvik
B108: Omsetning 2035, MEUR | C108: =L63 -> 2486.0392 | D108: =L71 -> 3096.2349 | E108: =(D108-C108)/C108 -> 0.24544894
B109: Omsetnings-CAGR 2025-2035 | C109: =('Forecast Base'!L52/'Forecast Base'!C52)^(1/10)-1 -> 0.053230559 | D109: =C104 -> 0.089077812 | E109: =(D109-C109)*100 -> 3.5847252
B110: EBITA-margin 2035 | C110: =M14 -> 0.17690804 | D110: =M16 -> 0.20162023 | E110: =+(D110-C110)*100000 -> 2471.2185

Sheet Peer Analyse
B2: TOMRA - Peer Analyse
B3: Brukt som et suplement til DCF - ikke hovedverdsettelsen
B5: EV, MEUR | C5: =('Historiske finansielle tall'!C4*('Historiske finansielle tall'!C5/1000000))/DCF!C6+DCF!C21+DCF!C22+DCF!C23 -> 3521.118
B7: Selskap | C7: Tomra-segment | D7: Relevans
B8: Envipco | C8: Collection | D8: Direkte RVM-konkurrent
B9: JBT Marel | C9: Food | D9: Matprosessering og automasjon
B10: GEA Group | C10: Food | D10: Prosessutstyr for mat og drikke
B11: Krones | C11: Recycling/emballasje | D11: PET-, emballasje og resirkuleringssystemer
B12: ANDRITZ | C12: Recycling | D12: Industrielt prosess- og resirkuleringsutstyr
B17: Trading comps -2027E | D17: 2026E | H17: 2027E
B18: Selskap | C18: Gruppe | D18: Salgsvekst | E18: EBIT-margin | F18: EV/Sales | G18: EV/EBIT | H18: Salgsvekst | I18: EBIT-margin | J18: EV/sales | K18: EV/EBIT | L18: P/E
B19: TOMRA (markedskonsensus) | C19: TOMRA | D19: =(1498-1318)/1318 -> 0.13657056 | E19: =165.3/1498 -> 0.11034713 | F19: 2.24 | G19: 20.4 | H19: =(1784-1498)/1498 -> 0.19092123 | I19: =273.1/1784 -> 0.15308296 | J19: =1.84 -> 1.84 | K19: 12 | L19: 14.5 | N19: Kilde: https://www.marketscreener.com/quote/stock/TOMRA-SYSTEMS-ASA-438799/valuation/
B20: TOMRA (egne estimater) | C20: TOMRA | D20: ='Forecast Base'!F45 -> 0.12209249 | E20: ='Forecast Base'!C56/'Forecast Base'!C52 -> 0.11015619 | F20: =C5/'Forecast Base'!F44 -> 2.3790695 | G20: =C5/'Forecast Base'!C56 -> 21.597238 | H20: ='Forecast Base'!G45 -> 0.083142077 | I20: ='Forecast Base'!D56/'Forecast Base'!D52 -> 0.1312628 | J20: =C5/'Forecast Base'!G44 -> 2.1964519 | K20: =C5/'Forecast Base'!D56 -> 16.73324
B21: Envipco | C21: Direkte Collection- peer | D21: =(123.6-90.35)/90.35 -> 0.36801328 | E21: =0.7215/123.6 -> 0.0058373786 | F21: 1.93 | G21: 330 | H21: =(267.6-123.6)/123.6 -> 1.1650485 | I21: =54.12/267.6 -> 0.20224215 | J21: 0.99 | K21: 4.91 | L21: 5.04 | N21: Kilde: https://www.marketscreener.com/quote/stock/ENVIPCO-HOLDING-N-V-46512764/valuation/
B22: JBT Marel | C22: Kjernepeer | D22: =(4028-3798)/3798 -> 0.060558189 | E22: =477/4028 -> 0.11842105 | F22: 2.12 | G22: 17.9 | H22: =(4225-4028)/4028 -> 0.048907646 | I22: =(554.9/4225) -> 0.13133728 | J22: 1.95 | K22: 14.8 | L22: 21.5 | N22: Kilde: https://www.marketscreener.com/quote/stock/JBT-MAREL-CORPORATION-3860953/
B23: GEA Group | C23: Kjernepeer | D23: =(5851-5495)/5495 -> 0.064786169 | E23: =762.5/5851 -> 0.1303196 | F23: 1.66 | G23: 12.7 | H23: =(6098-5851)/5851 -> 0.042215006 | I23: =825.7/6098 -> 0.13540505 | J23: 1.55 | K23: 11.5 | L23: 17.7 | N23: Kilde: https://www.marketscreener.com/quote/stock/GEA-GROUP-AG-436397/valuation/
B24: Krones | C24: Kjernepeer | D24: =(5791-5664)/5664 -> 0.022422316 | E24: =437.6/5791 -> 0.075565533 | F24: 0.53 | G24: 7.01 | H24: =(6104-5791)/5791 -> 0.054049387 | I24: =479.5/6104 -> 0.078555046 | J24: 0.48 | K24: 6.13 | L24: 10.3 | N24: Kilde: https://www.marketscreener.com/quote/stock/KRONES-AG-436341/valuation/
B25: ANDRITZ | C25: Kjernepeer | D25: =(8237-7883)/7883 -> 0.044906761 | E25: =650.2/8237 -> 0.078936506 | F25: 0.89 | G25: 11.2 | H25: =(8824-8237)/8237 -> 0.07126381 | I25: =746.9/8824 -> 0.084644152 | J25: 0.8 | K25: 9.45 | L25: 14.1 | N25: Kilde: https://www.marketscreener.com/quote/stock/ANDRITZ-AG-6491279/valuation/
B26: Kjernemedian | D26: =MEDIAN(D22:D25) -> 0.052732475 | E26: =MEDIAN(E22:E25) -> 0.098678779 | F26: =MEDIAN(F22:F25) -> 1.275 | G26: =MEDIAN(G22:G25) -> 11.95 | H26: =MEDIAN(H22:H25) -> 0.051478517 | I26: =MEDIAN(I22:I25) -> 0.10799072 | J26: =MEDIAN(J22:J25) -> 1.175 | K26: =MEDIAN(K22:K25) -> 10.475 | L26: =MEDIAN(L22:L25) -> 15.9
B27: TOMRA marked vs median | C27: Avvik mot kjernemedian | D27: =100000*(D19-D26) -> 8383.8087 | E27: =100000*(E19-E26) -> 1166.835 | F27: =F19/F26-1 -> 0.75686275 | G27: =G19/G26-1 -> 0.70711297 | H27: =(H19-H26)*100000 -> 13944.271 | I27: =(I19-I26)*100000 -> 4509.2244 | J27: =J19/J26-1 -> 0.56595745 | K27: =K19/K26-1 -> 0.14558473 | L27: =L19/L26-1 -> -0.088050314
B28: TOMRA (egne estimater) vs median | C28: Avvik mot kjernemedian | D28: =100000*(D20-D26) -> 6936.0019 | E28: =(E20-E26)*100000 -> 1147.741 | F28: =F20/F26-1 -> 0.86593684 | G28: =G20/G26-1 -> 0.80730027 | H28: =(H20-H26)*100000 -> 3166.3561 | I28: =(I20-I26)*100000 -> 2327.2085 | J28: =J20/J26-1 -> 0.86932076 | K28: =K20/K26-1 -> 0.59744531 | L28: -
B33: Verdsettelse basert på 2027E multipler
B34: Scenario | C34: 2027E EV/EBIT | D34: 2027E EBIT | E34: Implisitt EV, MEUR | F34: EK-verdi, MEUR | G34: EUR/aksje | H34: NOK/aksje
B35: Kjernemedian | C35: =K26 -> 10.475 | D35: ='Forecast Base'!D56 -> 210.42656 | E35: =D35*C35 -> 2204.2182 | F35: =E35-DCF!$C$21-DCF!$C$22-DCF!$C$23-DCF!$C$24 -> 1524.2182 | G35: =F35/(DCF!C5/1000000) -> 5.1486872 | H35: =G35*DCF!C6 -> 56.223665
B36: Moderat TOMRA premie | C36: 12 | D36: =D35 -> 210.42656 | E36: =D36*C36 -> 2525.1187 | F36: =E36-DCF!$C$21-DCF!$C$22-DCF!$C$23-DCF!$C$24 -> 1845.1187 | G36: =F36/(DCF!C5/1000000) -> 6.2326635 | H36: =G36*DCF!C6 -> 68.060685
B37: DCF-ekvivalent | C37: =DCF!C20/'Forecast Base'!D56 -> 14.529844 | D37: =D36 -> 210.42656 | E37: =D37*C37 -> 3057.465 | F37: =E37-DCF!$C$21-DCF!$C$22-DCF!$C$23-DCF!$C$24 -> 2377.465 | G37: =F37/(DCF!C5/1000000) -> 8.0308868 | H37: =G37*DCF!C6 -> 87.697284
B47: Metode | C47: Verdi per aksje
B48: DCF - base case | C48: =DCF!$D$99 -> 87.697284
B49: Peer-verdi -kjernemedian | C49: =H35 -> 56.223665
B50: Peer-verdi - moderat premie | C50: =H36 -> 68.060685
B51: Markedskurs | C51: ='Historiske finansielle tall'!$C$4 -> 104.8
